Classfile /G:/githubs/spring-boot-protocol/target/classes/com/github/netty/protocol/servlet/ServletContext.class
  Last modified 2018-12-22; size 25651 bytes
  MD5 checksum 3447c2f4384e4b65c62715f931d88e30
  Compiled from "ServletContext.java"
public class com.github.netty.protocol.servlet.ServletContext implements javax.servlet.ServletContext
  minor version: 0
  major version: 52
  flags: ACC_PUBLIC, ACC_SUPER
Constant pool:
    #1 = Methodref          #180.#470     // java/lang/Object."<init>":()V
    #2 = Methodref          #180.#471     // java/lang/Object.getClass:()Ljava/lang/Class;
    #3 = Methodref          #472.#473     // com/github/netty/core/util/LoggerFactoryX.getLogger:(Ljava/lang/Class;)Lcom/github/netty/core/util/LoggerX;
    #4 = Fieldref           #179.#474     // com/github/netty/protocol/servlet/ServletContext.logger:Lcom/github/netty/core/util/LoggerX;
    #5 = Fieldref           #179.#475     // com/github/netty/protocol/servlet/ServletContext.sessionTimeout:I
    #6 = Fieldref           #179.#476     // com/github/netty/protocol/servlet/ServletContext.responseWriterChunkMaxHeapByteLength:I
    #7 = Class              #477          // java/util/HashMap
    #8 = Methodref          #7.#478       // java/util/HashMap."<init>":(I)V
    #9 = Fieldref           #179.#479     // com/github/netty/protocol/servlet/ServletContext.attributeMap:Ljava/util/Map;
   #10 = Fieldref           #179.#480     // com/github/netty/protocol/servlet/ServletContext.initParamMap:Ljava/util/Map;
   #11 = Fieldref           #179.#481     // com/github/netty/protocol/servlet/ServletContext.servletRegistrationMap:Ljava/util/Map;
   #12 = Fieldref           #179.#482     // com/github/netty/protocol/servlet/ServletContext.filterRegistrationMap:Ljava/util/Map;
   #13 = Class              #483          // java/util/HashSet
   #14 = Class              #484          // javax/servlet/SessionTrackingMode
   #15 = Fieldref           #14.#485      // javax/servlet/SessionTrackingMode.COOKIE:Ljavax/servlet/SessionTrackingMode;
   #16 = Fieldref           #14.#486      // javax/servlet/SessionTrackingMode.URL:Ljavax/servlet/SessionTrackingMode;
   #17 = Methodref          #487.#488     // java/util/Arrays.asList:([Ljava/lang/Object;)Ljava/util/List;
   #18 = Methodref          #13.#489      // java/util/HashSet."<init>":(Ljava/util/Collection;)V
   #19 = Fieldref           #179.#490     // com/github/netty/protocol/servlet/ServletContext.defaultSessionTrackingModeSet:Ljava/util/Set;
   #20 = Class              #491          // com/github/netty/protocol/servlet/ServletErrorPageManager
   #21 = Methodref          #20.#470      // com/github/netty/protocol/servlet/ServletErrorPageManager."<init>":()V
   #22 = Fieldref           #179.#492     // com/github/netty/protocol/servlet/ServletContext.servletErrorPageManager:Lcom/github/netty/protocol/servlet/ServletErrorPageManager;
   #23 = Class              #493          // com/github/netty/protocol/servlet/util/MimeMappingsX
   #24 = Methodref          #23.#470      // com/github/netty/protocol/servlet/util/MimeMappingsX."<init>":()V
   #25 = Fieldref           #179.#494     // com/github/netty/protocol/servlet/ServletContext.mimeMappings:Lcom/github/netty/protocol/servlet/util/MimeMappingsX;
   #26 = Class              #495          // com/github/netty/protocol/servlet/ServletEventListenerManager
   #27 = Methodref          #26.#470      // com/github/netty/protocol/servlet/ServletEventListenerManager."<init>":()V
   #28 = Fieldref           #179.#496     // com/github/netty/protocol/servlet/ServletContext.servletEventListenerManager:Lcom/github/netty/protocol/servlet/ServletEventListenerManager;
   #29 = Class              #497          // com/github/netty/protocol/servlet/ServletSessionCookieConfig
   #30 = Methodref          #29.#470      // com/github/netty/protocol/servlet/ServletSessionCookieConfig."<init>":()V
   #31 = Fieldref           #179.#498     // com/github/netty/protocol/servlet/ServletContext.sessionCookieConfig:Lcom/github/netty/protocol/servlet/ServletSessionCookieConfig;
   #32 = Class              #499          // com/github/netty/protocol/servlet/util/UrlMapper
   #33 = Methodref          #32.#500      // com/github/netty/protocol/servlet/util/UrlMapper."<init>":(Z)V
   #34 = Fieldref           #179.#501     // com/github/netty/protocol/servlet/ServletContext.servletUrlMapper:Lcom/github/netty/protocol/servlet/util/UrlMapper;
   #35 = Fieldref           #179.#502     // com/github/netty/protocol/servlet/ServletContext.filterUrlMapper:Lcom/github/netty/protocol/servlet/util/UrlMapper;
   #36 = Methodref          #503.#504     // java/util/Objects.requireNonNull:(Ljava/lang/Object;)Ljava/lang/Object;
   #37 = Class              #505          // java/net/InetSocketAddress
   #38 = Fieldref           #179.#506     // com/github/netty/protocol/servlet/ServletContext.servletServerAddress:Ljava/net/InetSocketAddress;
   #39 = Class              #507          // java/lang/StringBuilder
   #40 = Methodref          #39.#470      // java/lang/StringBuilder."<init>":()V
   #41 = Methodref          #39.#508      // java/lang/StringBuilder.append:(C)Ljava/lang/StringBuilder;
   #42 = Methodref          #37.#509      // java/net/InetSocketAddress.getHostName:()Ljava/lang/String;
   #43 = Methodref          #510.#511     // com/github/netty/core/util/HostUtil.isLocalhost:(Ljava/lang/String;)Z
   #44 = String             #512          // localhost
   #45 = Methodref          #39.#513      // java/lang/StringBuilder.append:(Ljava/lang/String;)Ljava/lang/StringBuilder;
   #46 = Methodref          #39.#514      // java/lang/StringBuilder.toString:()Ljava/lang/String;
   #47 = Class              #515          // com/github/netty/core/util/ResourceManager
   #48 = Methodref          #47.#516      // com/github/netty/core/util/ResourceManager."<init>":(Ljava/lang/String;Ljava/lang/String;Ljava/lang/ClassLoader;)V
   #49 = Fieldref           #179.#517     // com/github/netty/protocol/servlet/ServletContext.resourceManager:Lcom/github/netty/core/util/ResourceManager;
   #50 = String             #518          // /
   #51 = Methodref          #47.#519      // com/github/netty/core/util/ResourceManager.mkdirs:(Ljava/lang/String;)Z
   #52 = Fieldref           #179.#520     // com/github/netty/protocol/servlet/ServletContext.asyncExecutorService:Ljava/util/concurrent/ExecutorService;
   #53 = Class              #521          // com/github/netty/core/util/ThreadPoolX
   #54 = String             #522          // Async
   #55 = Methodref          #53.#523      // com/github/netty/core/util/ThreadPoolX."<init>":(Ljava/lang/String;I)V
   #56 = Fieldref           #179.#524     // com/github/netty/protocol/servlet/ServletContext.servletContextName:Ljava/lang/String;
   #57 = Fieldref           #179.#525     // com/github/netty/protocol/servlet/ServletContext.serverHeader:Ljava/lang/String;
   #58 = Fieldref           #179.#526     // com/github/netty/protocol/servlet/ServletContext.contextPath:Ljava/lang/String;
   #59 = String             #527          // asyncTimeout
   #60 = Methodref          #179.#528     // com/github/netty/protocol/servlet/ServletContext.getInitParameter:(Ljava/lang/String;)Ljava/lang/String;
   #61 = Long               10000l
   #63 = Methodref          #529.#530     // java/lang/Long.parseLong:(Ljava/lang/String;)J
   #64 = Class              #531          // java/lang/NumberFormatException
   #65 = Fieldref           #179.#532     // com/github/netty/protocol/servlet/ServletContext.sessionService:Lcom/github/netty/protocol/servlet/SessionService;
   #66 = Methodref          #88.#533      // java/lang/String.lastIndexOf:(I)I
   #67 = Methodref          #88.#534      // java/lang/String.substring:(I)Ljava/lang/String;
   #68 = Methodref          #88.#535      // java/lang/String.length:()I
   #69 = Methodref          #23.#536      // com/github/netty/protocol/servlet/util/MimeMappingsX.get:(Ljava/lang/String;)Ljava/lang/String;
   #70 = Methodref          #47.#537      // com/github/netty/core/util/ResourceManager.getResourcePaths:(Ljava/lang/String;)Ljava/util/Set;
   #71 = Methodref          #47.#538      // com/github/netty/core/util/ResourceManager.getResource:(Ljava/lang/String;)Ljava/net/URL;
   #72 = Methodref          #47.#539      // com/github/netty/core/util/ResourceManager.getResourceAsStream:(Ljava/lang/String;)Ljava/io/InputStream;
   #73 = Methodref          #47.#540      // com/github/netty/core/util/ResourceManager.getRealPath:(Ljava/lang/String;)Ljava/lang/String;
   #74 = Methodref          #32.#541      // com/github/netty/protocol/servlet/util/UrlMapper.getMappingObjectByUri:(Ljava/lang/String;)Ljava/lang/Object;
   #75 = Class              #542          // com/github/netty/protocol/servlet/ServletRegistration
   #76 = Methodref          #543.#544     // com/github/netty/protocol/servlet/ServletFilterChain.newInstance:(Lcom/github/netty/protocol/servlet/ServletContext;Lcom/github/netty/protocol/servlet/ServletRegistration;)Lcom/github/netty/protocol/servlet/ServletFilterChain;
   #77 = Methodref          #543.#545     // com/github/netty/protocol/servlet/ServletFilterChain.getFilterRegistrationList:()Ljava/util/List;
   #78 = Methodref          #32.#546      // com/github/netty/protocol/servlet/util/UrlMapper.getMappingObjectsByUri:(Ljava/lang/String;Ljava/util/List;)Ljava/util/List;
   #79 = Methodref          #547.#548     // com/github/netty/protocol/servlet/ServletRequestDispatcher.newInstance:(Lcom/github/netty/protocol/servlet/ServletFilterChain;)Lcom/github/netty/protocol/servlet/ServletRequestDispatcher;
   #80 = Methodref          #547.#549     // com/github/netty/protocol/servlet/ServletRequestDispatcher.setPath:(Ljava/lang/String;)V
   #81 = Methodref          #179.#550     // com/github/netty/protocol/servlet/ServletContext.getServletRegistration:(Ljava/lang/String;)Lcom/github/netty/protocol/servlet/ServletRegistration;
   #82 = InterfaceMethodref #551.#552     // java/util/Map.values:()Ljava/util/Collection;
   #83 = InterfaceMethodref #553.#554     // java/util/Collection.iterator:()Ljava/util/Iterator;
   #84 = InterfaceMethodref #555.#556     // java/util/Iterator.hasNext:()Z
   #85 = InterfaceMethodref #555.#557     // java/util/Iterator.next:()Ljava/lang/Object;
   #86 = Class              #558          // com/github/netty/protocol/servlet/ServletFilterRegistration
   #87 = Methodref          #86.#559      // com/github/netty/protocol/servlet/ServletFilterRegistration.getServletNameMappings:()Ljava/util/Collection;
   #88 = Class              #560          // java/lang/String
   #89 = Methodref          #88.#561      // java/lang/String.equals:(Ljava/lang/Object;)Z
   #90 = InterfaceMethodref #562.#563     // java/util/List.add:(Ljava/lang/Object;)Z
   #91 = Methodref          #547.#564     // com/github/netty/protocol/servlet/ServletRequestDispatcher.setName:(Ljava/lang/String;)V
   #92 = InterfaceMethodref #551.#565     // java/util/Map.get:(Ljava/lang/Object;)Ljava/lang/Object;
   #93 = Methodref          #75.#566      // com/github/netty/protocol/servlet/ServletRegistration.getServlet:()Ljavax/servlet/Servlet;
   #94 = Class              #567          // java/util/ArrayList
   #95 = Methodref          #94.#470      // java/util/ArrayList."<init>":()V
   #96 = Methodref          #568.#569     // java/util/Collections.enumeration:(Ljava/util/Collection;)Ljava/util/Enumeration;
   #97 = Methodref          #75.#570      // com/github/netty/protocol/servlet/ServletRegistration.getName:()Ljava/lang/String;
   #98 = Methodref          #571.#572     // com/github/netty/core/util/LoggerX.debug:(Ljava/lang/String;)V
   #99 = Methodref          #571.#573     // com/github/netty/core/util/LoggerX.debug:(Ljava/lang/String;Ljava/lang/Throwable;)V
  #100 = Methodref          #574.#575     // com/github/netty/protocol/servlet/util/ServletUtil.getServerInfo:()Ljava/lang/String;
  #101 = String             #576          // (JDK
  #102 = Methodref          #88.#577      // java/lang/String.concat:(Ljava/lang/String;)Ljava/lang/String;
  #103 = Methodref          #574.#578     // com/github/netty/protocol/servlet/util/ServletUtil.getJvmVersion:()Ljava/lang/String;
  #104 = String             #579          // ;
  #105 = Methodref          #574.#580     // com/github/netty/protocol/servlet/util/ServletUtil.getOsName:()Ljava/lang/String;
  #106 = String             #581          //
  #107 = Methodref          #574.#582     // com/github/netty/protocol/servlet/util/ServletUtil.getArch:()Ljava/lang/String;
  #108 = String             #583          // )
  #109 = Methodref          #584.#585     // com/github/netty/core/util/TypeUtil.cast:(Ljava/lang/Object;Ljava/lang/Class;)Ljava/lang/Object;
  #110 = Methodref          #125.#586     // java/lang/Class.isAssignableFrom:(Ljava/lang/Class;)Z
  #111 = InterfaceMethodref #551.#587     // java/util/Map.keySet:()Ljava/util/Set;
  #112 = InterfaceMethodref #551.#588     // java/util/Map.putIfAbsent:(Ljava/lang/Object;Ljava/lang/Object;)Ljava/lang/Object;
  #113 = Methodref          #179.#589     // com/github/netty/protocol/servlet/ServletContext.removeAttribute:(Ljava/lang/String;)V
  #114 = InterfaceMethodref #551.#590     // java/util/Map.put:(Ljava/lang/Object;Ljava/lang/Object;)Ljava/lang/Object;
  #115 = Methodref          #179.#591     // com/github/netty/protocol/servlet/ServletContext.getServletEventListenerManager:()Lcom/github/netty/protocol/servlet/ServletEventListenerManager;
  #116 = Methodref          #26.#592      // com/github/netty/protocol/servlet/ServletEventListenerManager.hasServletContextAttributeListener:()Z
  #117 = Class              #593          // javax/servlet/ServletContextAttributeEvent
  #118 = Methodref          #117.#594     // javax/servlet/ServletContextAttributeEvent."<init>":(Ljavax/servlet/ServletContext;Ljava/lang/String;Ljava/lang/Object;)V
  #119 = Methodref          #26.#595      // com/github/netty/protocol/servlet/ServletEventListenerManager.onServletContextAttributeAdded:(Ljavax/servlet/ServletContextAttributeEvent;)V
  #120 = Methodref          #26.#596      // com/github/netty/protocol/servlet/ServletEventListenerManager.onServletContextAttributeReplaced:(Ljavax/servlet/ServletContextAttributeEvent;)V
  #121 = InterfaceMethodref #551.#597     // java/util/Map.remove:(Ljava/lang/Object;)Ljava/lang/Object;
  #122 = Methodref          #26.#598      // com/github/netty/protocol/servlet/ServletEventListenerManager.onServletContextAttributeRemoved:(Ljavax/servlet/ServletContextAttributeEvent;)V
  #123 = Methodref          #125.#599     // java/lang/Class.forName:(Ljava/lang/String;)Ljava/lang/Class;
  #124 = Methodref          #125.#600     // java/lang/Class.newInstance:()Ljava/lang/Object;
  #125 = Class              #601          // java/lang/Class
  #126 = Methodref          #179.#602     // com/github/netty/protocol/servlet/ServletContext.addServlet:(Ljava/lang/String;Ljava/lang/Class;)Lcom/github/netty/protocol/servlet/ServletRegistration;
  #127 = Class              #603          // java/lang/InstantiationException
  #128 = Class              #604          // java/lang/IllegalAccessException
  #129 = Class              #605          // java/lang/ClassNotFoundException
  #130 = Methodref          #606.#607     // java/lang/ReflectiveOperationException.printStackTrace:()V
  #131 = Methodref          #26.#608      // com/github/netty/protocol/servlet/ServletEventListenerManager.onServletAdded:(Ljavax/servlet/Servlet;)Ljavax/servlet/Servlet;
  #132 = Methodref          #75.#609      // com/github/netty/protocol/servlet/ServletRegistration."<init>":(Ljava/lang/String;Ljavax/servlet/Servlet;Lcom/github/netty/protocol/servlet/ServletContext;Lcom/github/netty/protocol/servlet/util/UrlMapper;)V
  #133 = Class              #610          // javax/servlet/Servlet
  #134 = Methodref          #179.#611     // com/github/netty/protocol/servlet/ServletContext.addServlet:(Ljava/lang/String;Ljavax/servlet/Servlet;)Lcom/github/netty/protocol/servlet/ServletRegistration;
  #135 = Methodref          #179.#612     // com/github/netty/protocol/servlet/ServletContext.addFilter:(Ljava/lang/String;Ljava/lang/Class;)Lcom/github/netty/protocol/servlet/ServletFilterRegistration;
  #136 = Methodref          #129.#607     // java/lang/ClassNotFoundException.printStackTrace:()V
  #137 = Methodref          #86.#613      // com/github/netty/protocol/servlet/ServletFilterRegistration."<init>":(Ljava/lang/String;Ljavax/servlet/Filter;Lcom/github/netty/protocol/servlet/ServletContext;Lcom/github/netty/protocol/servlet/util/UrlMapper;)V
  #138 = Class              #614          // javax/servlet/Filter
  #139 = Methodref          #179.#615     // com/github/netty/protocol/servlet/ServletContext.addFilter:(Ljava/lang/String;Ljavax/servlet/Filter;)Lcom/github/netty/protocol/servlet/ServletFilterRegistration;
  #140 = Class              #616          // javax/servlet/FilterRegistration
  #141 = Fieldref           #179.#617     // com/github/netty/protocol/servlet/ServletContext.sessionTrackingModeSet:Ljava/util/Set;
  #142 = Methodref          #179.#618     // com/github/netty/protocol/servlet/ServletContext.getDefaultSessionTrackingModes:()Ljava/util/Set;
  #143 = Methodref          #179.#619     // com/github/netty/protocol/servlet/ServletContext.addListener:(Ljava/lang/Class;)V
  #144 = Class              #620          // javax/servlet/ServletContextAttributeListener
  #145 = Methodref          #26.#621      // com/github/netty/protocol/servlet/ServletEventListenerManager.addServletContextAttributeListener:(Ljavax/servlet/ServletContextAttributeListener;)V
  #146 = Class              #622          // javax/servlet/ServletRequestListener
  #147 = Methodref          #26.#623      // com/github/netty/protocol/servlet/ServletEventListenerManager.addServletRequestListener:(Ljavax/servlet/ServletRequestListener;)V
  #148 = Class              #624          // javax/servlet/ServletRequestAttributeListener
  #149 = Methodref          #26.#625      // com/github/netty/protocol/servlet/ServletEventListenerManager.addServletRequestAttributeListener:(Ljavax/servlet/ServletRequestAttributeListener;)V
  #150 = Class              #626          // javax/servlet/http/HttpSessionIdListener
  #151 = Methodref          #26.#627      // com/github/netty/protocol/servlet/ServletEventListenerManager.addHttpSessionIdListenerListener:(Ljavax/servlet/http/HttpSessionIdListener;)V
  #152 = Class              #628          // javax/servlet/http/HttpSessionAttributeListener
  #153 = Methodref          #26.#629      // com/github/netty/protocol/servlet/ServletEventListenerManager.addHttpSessionAttributeListener:(Ljavax/servlet/http/HttpSessionAttributeListener;)V
  #154 = Class              #630          // javax/servlet/http/HttpSessionListener
  #155 = Methodref          #26.#631      // com/github/netty/protocol/servlet/ServletEventListenerManager.addHttpSessionListener:(Ljavax/servlet/http/HttpSessionListener;)V
  #156 = Class              #632          // javax/servlet/ServletContextListener
  #157 = Methodref          #26.#633      // com/github/netty/protocol/servlet/ServletEventListenerManager.addServletContextListener:(Ljavax/servlet/ServletContextListener;)V
  #158 = Class              #634          // java/lang/IllegalArgumentException
  #159 = String             #635          // applicationContext.addListener.iae.wrongType
  #160 = Methodref          #125.#570     // java/lang/Class.getName:()Ljava/lang/String;
  #161 = Methodref          #158.#636     // java/lang/IllegalArgumentException."<init>":(Ljava/lang/String;)V
  #162 = Class              #637          // java/util/EventListener
  #163 = Methodref          #179.#638     // com/github/netty/protocol/servlet/ServletContext.addListener:(Ljava/util/EventListener;)V
  #164 = Methodref          #47.#639      // com/github/netty/core/util/ResourceManager.getClassLoader:()Ljava/lang/ClassLoader;
  #165 = String             #640          //  (
  #166 = String             #641          // :
  #167 = String             #642          // user.name
  #168 = Methodref          #643.#536     // com/github/netty/core/util/SystemPropertyUtil.get:(Ljava/lang/String;)Ljava/lang/String;
  #169 = Fieldref           #179.#644     // com/github/netty/protocol/servlet/ServletContext.requestCharacterEncoding:Ljava/lang/String;
  #170 = Fieldref           #645.#646     // com/github/netty/protocol/servlet/util/HttpConstants.DEFAULT_CHARSET:Ljava/nio/charset/Charset;
  #171 = Methodref          #647.#648     // java/nio/charset/Charset.name:()Ljava/lang/String;
  #172 = Fieldref           #179.#649     // com/github/netty/protocol/servlet/ServletContext.responseCharacterEncoding:Ljava/lang/String;
  #173 = Methodref          #179.#650     // com/github/netty/protocol/servlet/ServletContext.getSessionCookieConfig:()Lcom/github/netty/protocol/servlet/ServletSessionCookieConfig;
  #174 = Methodref          #179.#651     // com/github/netty/protocol/servlet/ServletContext.addFilter:(Ljava/lang/String;Ljava/lang/String;)Lcom/github/netty/protocol/servlet/ServletFilterRegistration;
  #175 = Methodref          #179.#652     // com/github/netty/protocol/servlet/ServletContext.addServlet:(Ljava/lang/String;Ljava/lang/String;)Lcom/github/netty/protocol/servlet/ServletRegistration;
  #176 = Methodref          #179.#653     // com/github/netty/protocol/servlet/ServletContext.getNamedDispatcher:(Ljava/lang/String;)Lcom/github/netty/protocol/servlet/ServletRequestDispatcher;
  #177 = Methodref          #179.#654     // com/github/netty/protocol/servlet/ServletContext.getRequestDispatcher:(Ljava/lang/String;)Lcom/github/netty/protocol/servlet/ServletRequestDispatcher;
  #178 = Methodref          #179.#655     // com/github/netty/protocol/servlet/ServletContext.getContext:(Ljava/lang/String;)Lcom/github/netty/protocol/servlet/ServletContext;
  #179 = Class              #656          // com/github/netty/protocol/servlet/ServletContext
  #180 = Class              #657          // java/lang/Object
  #181 = Class              #658          // javax/servlet/ServletContext
  #182 = Utf8               logger
  #183 = Utf8               Lcom/github/netty/core/util/LoggerX;
  #184 = Utf8               sessionTimeout
  #185 = Utf8               I
  #186 = Utf8               responseWriterChunkMaxHeapByteLength
  #187 = Utf8               attributeMap
  #188 = Utf8               Ljava/util/Map;
  #189 = Utf8               Signature
  #190 = Utf8               Ljava/util/Map<Ljava/lang/String;Ljava/lang/Object;>;
  #191 = Utf8               initParamMap
  #192 = Utf8               Ljava/util/Map<Ljava/lang/String;Ljava/lang/String;>;
  #193 = Utf8               servletRegistrationMap
  #194 = Utf8               Ljava/util/Map<Ljava/lang/String;Lcom/github/netty/protocol/servlet/ServletRegistration;>;
  #195 = Utf8               filterRegistrationMap
  #196 = Utf8               Ljava/util/Map<Ljava/lang/String;Lcom/github/netty/protocol/servlet/ServletFilterRegistration;>;
  #197 = Utf8               defaultSessionTrackingModeSet
  #198 = Utf8               Ljava/util/Set;
  #199 = Utf8               Ljava/util/Set<Ljavax/servlet/SessionTrackingMode;>;
  #200 = Utf8               servletErrorPageManager
  #201 = Utf8               Lcom/github/netty/protocol/servlet/ServletErrorPageManager;
  #202 = Utf8               mimeMappings
  #203 = Utf8               Lcom/github/netty/protocol/servlet/util/MimeMappingsX;
  #204 = Utf8               servletEventListenerManager
  #205 = Utf8               Lcom/github/netty/protocol/servlet/ServletEventListenerManager;
  #206 = Utf8               sessionCookieConfig
  #207 = Utf8               Lcom/github/netty/protocol/servlet/ServletSessionCookieConfig;
  #208 = Utf8               servletUrlMapper
  #209 = Utf8               Lcom/github/netty/protocol/servlet/util/UrlMapper;
  #210 = Utf8               Lcom/github/netty/protocol/servlet/util/UrlMapper<Lcom/github/netty/protocol/servlet/ServletRegistration;>;
  #211 = Utf8               filterUrlMapper
  #212 = Utf8               Lcom/github/netty/protocol/servlet/util/UrlMapper<Lcom/github/netty/protocol/servlet/ServletFilterRegistration;>;
  #213 = Utf8               resourceManager
  #214 = Utf8               Lcom/github/netty/core/util/ResourceManager;
  #215 = Utf8               asyncExecutorService
  #216 = Utf8               Ljava/util/concurrent/ExecutorService;
  #217 = Utf8               sessionService
  #218 = Utf8               Lcom/github/netty/protocol/servlet/SessionService;
  #219 = Utf8               sessionTrackingModeSet
  #220 = Utf8               serverHeader
  #221 = Utf8               Ljava/lang/String;
  #222 = Utf8               contextPath
  #223 = Utf8               requestCharacterEncoding
  #224 = Utf8               responseCharacterEncoding
  #225 = Utf8               servletContextName
  #226 = Utf8               servletServerAddress
  #227 = Utf8               Ljava/net/InetSocketAddress;
  #228 = Utf8               <init>
  #229 = Utf8               (Ljava/net/InetSocketAddress;Ljava/lang/ClassLoader;Ljava/lang/String;)V
  #230 = Utf8               Code
  #231 = Utf8               LineNumberTable
  #232 = Utf8               LocalVariableTable
  #233 = Utf8               this
  #234 = Utf8               Lcom/github/netty/protocol/servlet/ServletContext;
  #235 = Utf8               socketAddress
  #236 = Utf8               classLoader
  #237 = Utf8               Ljava/lang/ClassLoader;
  #238 = Utf8               docBase
  #239 = Utf8               workspace
  #240 = Utf8               StackMapTable
  #241 = Class              #656          // com/github/netty/protocol/servlet/ServletContext
  #242 = Class              #505          // java/net/InetSocketAddress
  #243 = Class              #659          // java/lang/ClassLoader
  #244 = Class              #560          // java/lang/String
  #245 = Class              #507          // java/lang/StringBuilder
  #246 = Utf8               getAsyncExecutorService
  #247 = Utf8               ()Ljava/util/concurrent/ExecutorService;
  #248 = Class              #657          // java/lang/Object
  #249 = Class              #660          // java/lang/Throwable
  #250 = Utf8               getMimeMappings
  #251 = Utf8               ()Lcom/github/netty/protocol/servlet/util/MimeMappingsX;
  #252 = Utf8               getResourceManager
  #253 = Utf8               ()Lcom/github/netty/core/util/ResourceManager;
  #254 = Utf8               getErrorPageManager
  #255 = Utf8               ()Lcom/github/netty/protocol/servlet/ServletErrorPageManager;
  #256 = Utf8               setServletContextName
  #257 = Utf8               (Ljava/lang/String;)V
  #258 = Utf8               setServerHeader
  #259 = Utf8               getServerHeader
  #260 = Utf8               ()Ljava/lang/String;
  #261 = Utf8               setContextPath
  #262 = Utf8               getServletEventListenerManager
  #263 = Utf8               ()Lcom/github/netty/protocol/servlet/ServletEventListenerManager;
  #264 = Utf8               getAsyncTimeout
  #265 = Utf8               ()J
  #266 = Utf8               e
  #267 = Utf8               Ljava/lang/NumberFormatException;
  #268 = Utf8               value
  #269 = Class              #531          // java/lang/NumberFormatException
  #270 = Utf8               getResponseWriterChunkMaxHeapByteLength
  #271 = Utf8               ()I
  #272 = Utf8               setResponseWriterChunkMaxHeapByteLength
  #273 = Utf8               (I)V
  #274 = Utf8               getServletServerAddress
  #275 = Utf8               ()Ljava/net/InetSocketAddress;
  #276 = Utf8               setSessionService
  #277 = Utf8               (Lcom/github/netty/protocol/servlet/SessionService;)V
  #278 = Utf8               getSessionService
  #279 = Utf8               ()Lcom/github/netty/protocol/servlet/SessionService;
  #280 = Utf8               getSessionTimeout
  #281 = Utf8               setSessionTimeout
  #282 = Utf8               getContextPath
  #283 = Utf8               getContext
  #284 = Utf8               (Ljava/lang/String;)Lcom/github/netty/protocol/servlet/ServletContext;
  #285 = Utf8               uripath
  #286 = Utf8               getMajorVersion
  #287 = Utf8               getMinorVersion
  #288 = Utf8               getEffectiveMajorVersion
  #289 = Utf8               getEffectiveMinorVersion
  #290 = Utf8               getMimeType
  #291 = Utf8               (Ljava/lang/String;)Ljava/lang/String;
  #292 = Utf8               file
  #293 = Utf8               period
  #294 = Utf8               extension
  #295 = Utf8               getResourcePaths
  #296 = Utf8               (Ljava/lang/String;)Ljava/util/Set;
  #297 = Utf8               path
  #298 = Utf8               (Ljava/lang/String;)Ljava/util/Set<Ljava/lang/String;>;
  #299 = Utf8               getResource
  #300 = Utf8               (Ljava/lang/String;)Ljava/net/URL;
  #301 = Utf8               Exceptions
  #302 = Class              #661          // java/net/MalformedURLException
  #303 = Utf8               getResourceAsStream
  #304 = Utf8               (Ljava/lang/String;)Ljava/io/InputStream;
  #305 = Utf8               getRealPath
  #306 = Utf8               getRequestDispatcher
  #307 = Utf8               (Ljava/lang/String;)Lcom/github/netty/protocol/servlet/ServletRequestDispatcher;
  #308 = Utf8               servletRegistration
  #309 = Utf8               Lcom/github/netty/protocol/servlet/ServletRegistration;
  #310 = Utf8               filterChain
  #311 = Utf8               Lcom/github/netty/protocol/servlet/ServletFilterChain;
  #312 = Utf8               dispatcher
  #313 = Utf8               Lcom/github/netty/protocol/servlet/ServletRequestDispatcher;
  #314 = Class              #542          // com/github/netty/protocol/servlet/ServletRegistration
  #315 = Utf8               getNamedDispatcher
  #316 = Utf8               servletName
  #317 = Utf8               registration
  #318 = Utf8               Lcom/github/netty/protocol/servlet/ServletFilterRegistration;
  #319 = Utf8               name
  #320 = Utf8               filterList
  #321 = Utf8               Ljava/util/List;
  #322 = Utf8               LocalVariableTypeTable
  #323 = Utf8               Ljava/util/List<Lcom/github/netty/protocol/servlet/ServletFilterRegistration;>;
  #324 = Class              #662          // com/github/netty/protocol/servlet/ServletFilterChain
  #325 = Class              #663          // java/util/List
  #326 = Class              #664          // java/util/Iterator
  #327 = Class              #558          // com/github/netty/protocol/servlet/ServletFilterRegistration
  #328 = Utf8               getServlet
  #329 = Utf8               (Ljava/lang/String;)Ljavax/servlet/Servlet;
  #330 = Class              #665          // javax/servlet/ServletException
  #331 = Utf8               getServlets
  #332 = Utf8               ()Ljava/util/Enumeration;
  #333 = Utf8               list
  #334 = Utf8               Ljava/util/List<Ljavax/servlet/Servlet;>;
  #335 = Utf8               ()Ljava/util/Enumeration<Ljavax/servlet/Servlet;>;
  #336 = Utf8               getServletNames
  #337 = Utf8               Ljava/util/List<Ljava/lang/String;>;
  #338 = Utf8               ()Ljava/util/Enumeration<Ljava/lang/String;>;
  #339 = Utf8               log
  #340 = Utf8               msg
  #341 = Utf8               (Ljava/lang/Exception;Ljava/lang/String;)V
  #342 = Utf8               exception
  #343 = Utf8               Ljava/lang/Exception;
  #344 = Utf8               (Ljava/lang/String;Ljava/lang/Throwable;)V
  #345 = Utf8               message
  #346 = Utf8               throwable
  #347 = Utf8               Ljava/lang/Throwable;
  #348 = Utf8               getServerInfo
  #349 = Utf8               getInitParameter
  #350 = Utf8               (Ljava/lang/String;Ljava/lang/Object;)Ljava/lang/Object;
  #351 = Utf8               def
  #352 = Utf8               Ljava/lang/Object;
  #353 = Utf8               clazz
  #354 = Utf8               Ljava/lang/Class;
  #355 = Utf8               valCast
  #356 = Utf8               TT;
  #357 = Utf8               Ljava/lang/Class<*>;
  #358 = Class              #601          // java/lang/Class
  #359 = Utf8               <T:Ljava/lang/Object;>(Ljava/lang/String;TT;)TT;
  #360 = Utf8               getInitParameterNames
  #361 = Utf8               setInitParameter
  #362 = Utf8               (Ljava/lang/String;Ljava/lang/String;)Z
  #363 = Utf8               getAttribute
  #364 = Utf8               (Ljava/lang/String;)Ljava/lang/Object;
  #365 = Utf8               getAttributeNames
  #366 = Utf8               setAttribute
  #367 = Utf8               (Ljava/lang/String;Ljava/lang/Object;)V
  #368 = Utf8               object
  #369 = Utf8               oldObject
  #370 = Utf8               listenerManager
  #371 = Class              #495          // com/github/netty/protocol/servlet/ServletEventListenerManager
  #372 = Utf8               removeAttribute
  #373 = Utf8               getServletContextName
  #374 = Utf8               addServlet
  #375 = Utf8               (Ljava/lang/String;Ljava/lang/String;)Lcom/github/netty/protocol/servlet/ServletRegistration;
  #376 = Utf8               Ljava/lang/ReflectiveOperationException;
  #377 = Utf8               className
  #378 = Class              #666          // java/lang/ReflectiveOperationException
  #379 = Utf8               (Ljava/lang/String;Ljavax/servlet/Servlet;)Lcom/github/netty/protocol/servlet/ServletRegistration;
  #380 = Utf8               servlet
  #381 = Utf8               Ljavax/servlet/Servlet;
  #382 = Utf8               newServlet
  #383 = Class              #610          // javax/servlet/Servlet
  #384 = Utf8               (Ljava/lang/String;Ljava/lang/Class;)Lcom/github/netty/protocol/servlet/ServletRegistration;
  #385 = Utf8               servletClass
  #386 = Utf8               Ljava/lang/Class<+Ljavax/servlet/Servlet;>;
  #387 = Utf8               (Ljava/lang/String;Ljava/lang/Class<+Ljavax/servlet/Servlet;>;)Lcom/github/netty/protocol/servlet/ServletRegistration;
  #388 = Utf8               createServlet
  #389 = Utf8               (Ljava/lang/Class;)Ljavax/servlet/Servlet;
  #390 = Utf8               Ljava/lang/Class<TT;>;
  #391 = Utf8               <T::Ljavax/servlet/Servlet;>(Ljava/lang/Class<TT;>;)TT;
  #392 = Utf8               getServletRegistration
  #393 = Utf8               (Ljava/lang/String;)Lcom/github/netty/protocol/servlet/ServletRegistration;
  #394 = Utf8               getServletRegistrations
  #395 = Utf8               ()Ljava/util/Map;
  #396 = Utf8               ()Ljava/util/Map<Ljava/lang/String;Lcom/github/netty/protocol/servlet/ServletRegistration;>;
  #397 = Utf8               addFilter
  #398 = Utf8               (Ljava/lang/String;Ljava/lang/String;)Lcom/github/netty/protocol/servlet/ServletFilterRegistration;
  #399 = Utf8               Ljava/lang/ClassNotFoundException;
  #400 = Utf8               filterName
  #401 = Class              #605          // java/lang/ClassNotFoundException
  #402 = Utf8               (Ljava/lang/String;Ljavax/servlet/Filter;)Lcom/github/netty/protocol/servlet/ServletFilterRegistration;
  #403 = Utf8               filter
  #404 = Utf8               Ljavax/servlet/Filter;
  #405 = Utf8               (Ljava/lang/String;Ljava/lang/Class;)Lcom/github/netty/protocol/servlet/ServletFilterRegistration;
  #406 = Utf8               filterClass
  #407 = Utf8               Ljava/lang/Class<+Ljavax/servlet/Filter;>;
  #408 = Utf8               (Ljava/lang/String;Ljava/lang/Class<+Ljavax/servlet/Filter;>;)Lcom/github/netty/protocol/servlet/ServletFilterRegistration;
  #409 = Utf8               createFilter
  #410 = Utf8               (Ljava/lang/Class;)Ljavax/servlet/Filter;
  #411 = Utf8               <T::Ljavax/servlet/Filter;>(Ljava/lang/Class<TT;>;)TT;
  #412 = Utf8               getFilterRegistration
  #413 = Utf8               (Ljava/lang/String;)Ljavax/servlet/FilterRegistration;
  #414 = Utf8               getFilterRegistrations
  #415 = Utf8               ()Ljava/util/Map<Ljava/lang/String;Lcom/github/netty/protocol/servlet/ServletFilterRegistration;>;
  #416 = Utf8               getSessionCookieConfig
  #417 = Utf8               ()Lcom/github/netty/protocol/servlet/ServletSessionCookieConfig;
  #418 = Utf8               setSessionTrackingModes
  #419 = Utf8               (Ljava/util/Set;)V
  #420 = Utf8               sessionTrackingModes
  #421 = Utf8               (Ljava/util/Set<Ljavax/servlet/SessionTrackingMode;>;)V
  #422 = Utf8               getDefaultSessionTrackingModes
  #423 = Utf8               ()Ljava/util/Set;
  #424 = Utf8               ()Ljava/util/Set<Ljavax/servlet/SessionTrackingMode;>;
  #425 = Utf8               getEffectiveSessionTrackingModes
  #426 = Utf8               addListener
  #427 = Utf8               (Ljava/util/EventListener;)V
  #428 = Utf8               listener
  #429 = Utf8               Ljava/util/EventListener;
  #430 = Utf8               <T::Ljava/util/EventListener;>(TT;)V
  #431 = Utf8               (Ljava/lang/Class;)V
  #432 = Utf8               listenerClass
  #433 = Utf8               Ljava/lang/Class<+Ljava/util/EventListener;>;
  #434 = Utf8               (Ljava/lang/Class<+Ljava/util/EventListener;>;)V
  #435 = Utf8               createListener
  #436 = Utf8               (Ljava/lang/Class;)Ljava/util/EventListener;
  #437 = Utf8               <T::Ljava/util/EventListener;>(Ljava/lang/Class<TT;>;)TT;
  #438 = Utf8               getJspConfigDescriptor
  #439 = Utf8               ()Ljavax/servlet/descriptor/JspConfigDescriptor;
  #440 = Utf8               getClassLoader
  #441 = Utf8               ()Ljava/lang/ClassLoader;
  #442 = Utf8               declareRoles
  #443 = Utf8               ([Ljava/lang/String;)V
  #444 = Utf8               roleNames
  #445 = Utf8               [Ljava/lang/String;
  #446 = Utf8               getVirtualServerName
  #447 = Utf8               getRequestCharacterEncoding
  #448 = Utf8               setRequestCharacterEncoding
  #449 = Utf8               getResponseCharacterEncoding
  #450 = Utf8               setResponseCharacterEncoding
  #451 = Utf8               addJspFile
  #452 = Class              #668          // javax/servlet/ServletRegistration$Dynamic
  #453 = Utf8               Dynamic
  #454 = Utf8               InnerClasses
  #455 = Utf8               (Ljava/lang/String;Ljava/lang/String;)Ljavax/servlet/ServletRegistration$Dynamic;
  #456 = Utf8               jspName
  #457 = Utf8               jspFile
  #458 = Utf8               ()Ljavax/servlet/SessionCookieConfig;
  #459 = Class              #669          // javax/servlet/FilterRegistration$Dynamic
  #460 = Utf8               (Ljava/lang/String;Ljava/lang/Class;)Ljavax/servlet/FilterRegistration$Dynamic;
  #461 = Utf8               (Ljava/lang/String;Ljavax/servlet/Filter;)Ljavax/servlet/FilterRegistration$Dynamic;
  #462 = Utf8               (Ljava/lang/String;Ljava/lang/String;)Ljavax/servlet/FilterRegistration$Dynamic;
  #463 = Utf8               (Ljava/lang/String;)Ljavax/servlet/ServletRegistration;
  #464 = Utf8               (Ljava/lang/String;Ljava/lang/Class;)Ljavax/servlet/ServletRegistration$Dynamic;
  #465 = Utf8               (Ljava/lang/String;Ljavax/servlet/Servlet;)Ljavax/servlet/ServletRegistration$Dynamic;
  #466 = Utf8               (Ljava/lang/String;)Ljavax/servlet/RequestDispatcher;
  #467 = Utf8               (Ljava/lang/String;)Ljavax/servlet/ServletContext;
  #468 = Utf8               SourceFile
  #469 = Utf8               ServletContext.java
  #470 = NameAndType        #228:#670     // "<init>":()V
  #471 = NameAndType        #671:#672     // getClass:()Ljava/lang/Class;
  #472 = Class              #673          // com/github/netty/core/util/LoggerFactoryX
  #473 = NameAndType        #674:#675     // getLogger:(Ljava/lang/Class;)Lcom/github/netty/core/util/LoggerX;
  #474 = NameAndType        #182:#183     // logger:Lcom/github/netty/core/util/LoggerX;
  #475 = NameAndType        #184:#185     // sessionTimeout:I
  #476 = NameAndType        #186:#185     // responseWriterChunkMaxHeapByteLength:I
  #477 = Utf8               java/util/HashMap
  #478 = NameAndType        #228:#273     // "<init>":(I)V
  #479 = NameAndType        #187:#188     // attributeMap:Ljava/util/Map;
  #480 = NameAndType        #191:#188     // initParamMap:Ljava/util/Map;
  #481 = NameAndType        #193:#188     // servletRegistrationMap:Ljava/util/Map;
  #482 = NameAndType        #195:#188     // filterRegistrationMap:Ljava/util/Map;
  #483 = Utf8               java/util/HashSet
  #484 = Utf8               javax/servlet/SessionTrackingMode
  #485 = NameAndType        #676:#677     // COOKIE:Ljavax/servlet/SessionTrackingMode;
  #486 = NameAndType        #678:#677     // URL:Ljavax/servlet/SessionTrackingMode;
  #487 = Class              #679          // java/util/Arrays
  #488 = NameAndType        #680:#681     // asList:([Ljava/lang/Object;)Ljava/util/List;
  #489 = NameAndType        #228:#682     // "<init>":(Ljava/util/Collection;)V
  #490 = NameAndType        #197:#198     // defaultSessionTrackingModeSet:Ljava/util/Set;
  #491 = Utf8               com/github/netty/protocol/servlet/ServletErrorPageManager
  #492 = NameAndType        #200:#201     // servletErrorPageManager:Lcom/github/netty/protocol/servlet/ServletErrorPageManager;
  #493 = Utf8               com/github/netty/protocol/servlet/util/MimeMappingsX
  #494 = NameAndType        #202:#203     // mimeMappings:Lcom/github/netty/protocol/servlet/util/MimeMappingsX;
  #495 = Utf8               com/github/netty/protocol/servlet/ServletEventListenerManager
  #496 = NameAndType        #204:#205     // servletEventListenerManager:Lcom/github/netty/protocol/servlet/ServletEventListenerManager;
  #497 = Utf8               com/github/netty/protocol/servlet/ServletSessionCookieConfig
  #498 = NameAndType        #206:#207     // sessionCookieConfig:Lcom/github/netty/protocol/servlet/ServletSessionCookieConfig;
  #499 = Utf8               com/github/netty/protocol/servlet/util/UrlMapper
  #500 = NameAndType        #228:#683     // "<init>":(Z)V
  #501 = NameAndType        #208:#209     // servletUrlMapper:Lcom/github/netty/protocol/servlet/util/UrlMapper;
  #502 = NameAndType        #211:#209     // filterUrlMapper:Lcom/github/netty/protocol/servlet/util/UrlMapper;
  #503 = Class              #684          // java/util/Objects
  #504 = NameAndType        #685:#686     // requireNonNull:(Ljava/lang/Object;)Ljava/lang/Object;
  #505 = Utf8               java/net/InetSocketAddress
  #506 = NameAndType        #226:#227     // servletServerAddress:Ljava/net/InetSocketAddress;
  #507 = Utf8               java/lang/StringBuilder
  #508 = NameAndType        #687:#688     // append:(C)Ljava/lang/StringBuilder;
  #509 = NameAndType        #689:#260     // getHostName:()Ljava/lang/String;
  #510 = Class              #690          // com/github/netty/core/util/HostUtil
  #511 = NameAndType        #691:#692     // isLocalhost:(Ljava/lang/String;)Z
  #512 = Utf8               localhost
  #513 = NameAndType        #687:#693     // append:(Ljava/lang/String;)Ljava/lang/StringBuilder;
  #514 = NameAndType        #694:#260     // toString:()Ljava/lang/String;
  #515 = Utf8               com/github/netty/core/util/ResourceManager
  #516 = NameAndType        #228:#695     // "<init>":(Ljava/lang/String;Ljava/lang/String;Ljava/lang/ClassLoader;)V
  #517 = NameAndType        #213:#214     // resourceManager:Lcom/github/netty/core/util/ResourceManager;
  #518 = Utf8               /
  #519 = NameAndType        #696:#692     // mkdirs:(Ljava/lang/String;)Z
  #520 = NameAndType        #215:#216     // asyncExecutorService:Ljava/util/concurrent/ExecutorService;
  #521 = Utf8               com/github/netty/core/util/ThreadPoolX
  #522 = Utf8               Async
  #523 = NameAndType        #228:#697     // "<init>":(Ljava/lang/String;I)V
  #524 = NameAndType        #225:#221     // servletContextName:Ljava/lang/String;
  #525 = NameAndType        #220:#221     // serverHeader:Ljava/lang/String;
  #526 = NameAndType        #222:#221     // contextPath:Ljava/lang/String;
  #527 = Utf8               asyncTimeout
  #528 = NameAndType        #349:#291     // getInitParameter:(Ljava/lang/String;)Ljava/lang/String;
  #529 = Class              #698          // java/lang/Long
  #530 = NameAndType        #699:#700     // parseLong:(Ljava/lang/String;)J
  #531 = Utf8               java/lang/NumberFormatException
  #532 = NameAndType        #217:#218     // sessionService:Lcom/github/netty/protocol/servlet/SessionService;
  #533 = NameAndType        #701:#702     // lastIndexOf:(I)I
  #534 = NameAndType        #703:#704     // substring:(I)Ljava/lang/String;
  #535 = NameAndType        #705:#271     // length:()I
  #536 = NameAndType        #706:#291     // get:(Ljava/lang/String;)Ljava/lang/String;
  #537 = NameAndType        #295:#296     // getResourcePaths:(Ljava/lang/String;)Ljava/util/Set;
  #538 = NameAndType        #299:#300     // getResource:(Ljava/lang/String;)Ljava/net/URL;
  #539 = NameAndType        #303:#304     // getResourceAsStream:(Ljava/lang/String;)Ljava/io/InputStream;
  #540 = NameAndType        #305:#291     // getRealPath:(Ljava/lang/String;)Ljava/lang/String;
  #541 = NameAndType        #707:#364     // getMappingObjectByUri:(Ljava/lang/String;)Ljava/lang/Object;
  #542 = Utf8               com/github/netty/protocol/servlet/ServletRegistration
  #543 = Class              #662          // com/github/netty/protocol/servlet/ServletFilterChain
  #544 = NameAndType        #708:#709     // newInstance:(Lcom/github/netty/protocol/servlet/ServletContext;Lcom/github/netty/protocol/servlet/ServletRegistration;)Lcom/github/netty/protocol/servlet/ServletFilterChain;
  #545 = NameAndType        #710:#711     // getFilterRegistrationList:()Ljava/util/List;
  #546 = NameAndType        #712:#713     // getMappingObjectsByUri:(Ljava/lang/String;Ljava/util/List;)Ljava/util/List;
  #547 = Class              #714          // com/github/netty/protocol/servlet/ServletRequestDispatcher
  #548 = NameAndType        #708:#715     // newInstance:(Lcom/github/netty/protocol/servlet/ServletFilterChain;)Lcom/github/netty/protocol/servlet/ServletRequestDispatcher;
  #549 = NameAndType        #716:#257     // setPath:(Ljava/lang/String;)V
  #550 = NameAndType        #392:#393     // getServletRegistration:(Ljava/lang/String;)Lcom/github/netty/protocol/servlet/ServletRegistration;
  #551 = Class              #717          // java/util/Map
  #552 = NameAndType        #718:#719     // values:()Ljava/util/Collection;
  #553 = Class              #720          // java/util/Collection
  #554 = NameAndType        #721:#722     // iterator:()Ljava/util/Iterator;
  #555 = Class              #664          // java/util/Iterator
  #556 = NameAndType        #723:#724     // hasNext:()Z
  #557 = NameAndType        #725:#726     // next:()Ljava/lang/Object;
  #558 = Utf8               com/github/netty/protocol/servlet/ServletFilterRegistration
  #559 = NameAndType        #727:#719     // getServletNameMappings:()Ljava/util/Collection;
  #560 = Utf8               java/lang/String
  #561 = NameAndType        #728:#729     // equals:(Ljava/lang/Object;)Z
  #562 = Class              #663          // java/util/List
  #563 = NameAndType        #730:#729     // add:(Ljava/lang/Object;)Z
  #564 = NameAndType        #731:#257     // setName:(Ljava/lang/String;)V
  #565 = NameAndType        #706:#686     // get:(Ljava/lang/Object;)Ljava/lang/Object;
  #566 = NameAndType        #328:#732     // getServlet:()Ljavax/servlet/Servlet;
  #567 = Utf8               java/util/ArrayList
  #568 = Class              #733          // java/util/Collections
  #569 = NameAndType        #734:#735     // enumeration:(Ljava/util/Collection;)Ljava/util/Enumeration;
  #570 = NameAndType        #736:#260     // getName:()Ljava/lang/String;
  #571 = Class              #737          // com/github/netty/core/util/LoggerX
  #572 = NameAndType        #738:#257     // debug:(Ljava/lang/String;)V
  #573 = NameAndType        #738:#344     // debug:(Ljava/lang/String;Ljava/lang/Throwable;)V
  #574 = Class              #739          // com/github/netty/protocol/servlet/util/ServletUtil
  #575 = NameAndType        #348:#260     // getServerInfo:()Ljava/lang/String;
  #576 = Utf8               (JDK
  #577 = NameAndType        #740:#291     // concat:(Ljava/lang/String;)Ljava/lang/String;
  #578 = NameAndType        #741:#260     // getJvmVersion:()Ljava/lang/String;
  #579 = Utf8               ;
  #580 = NameAndType        #742:#260     // getOsName:()Ljava/lang/String;
  #581 = Utf8
  #582 = NameAndType        #743:#260     // getArch:()Ljava/lang/String;
  #583 = Utf8               )
  #584 = Class              #744          // com/github/netty/core/util/TypeUtil
  #585 = NameAndType        #745:#746     // cast:(Ljava/lang/Object;Ljava/lang/Class;)Ljava/lang/Object;
  #586 = NameAndType        #747:#748     // isAssignableFrom:(Ljava/lang/Class;)Z
  #587 = NameAndType        #749:#423     // keySet:()Ljava/util/Set;
  #588 = NameAndType        #750:#751     // putIfAbsent:(Ljava/lang/Object;Ljava/lang/Object;)Ljava/lang/Object;
  #589 = NameAndType        #372:#257     // removeAttribute:(Ljava/lang/String;)V
  #590 = NameAndType        #752:#751     // put:(Ljava/lang/Object;Ljava/lang/Object;)Ljava/lang/Object;
  #591 = NameAndType        #262:#263     // getServletEventListenerManager:()Lcom/github/netty/protocol/servlet/ServletEventListenerManager;
  #592 = NameAndType        #753:#724     // hasServletContextAttributeListener:()Z
  #593 = Utf8               javax/servlet/ServletContextAttributeEvent
  #594 = NameAndType        #228:#754     // "<init>":(Ljavax/servlet/ServletContext;Ljava/lang/String;Ljava/lang/Object;)V
  #595 = NameAndType        #755:#756     // onServletContextAttributeAdded:(Ljavax/servlet/ServletContextAttributeEvent;)V
  #596 = NameAndType        #757:#756     // onServletContextAttributeReplaced:(Ljavax/servlet/ServletContextAttributeEvent;)V
  #597 = NameAndType        #758:#686     // remove:(Ljava/lang/Object;)Ljava/lang/Object;
  #598 = NameAndType        #759:#756     // onServletContextAttributeRemoved:(Ljavax/servlet/ServletContextAttributeEvent;)V
  #599 = NameAndType        #760:#761     // forName:(Ljava/lang/String;)Ljava/lang/Class;
  #600 = NameAndType        #708:#726     // newInstance:()Ljava/lang/Object;
  #601 = Utf8               java/lang/Class
  #602 = NameAndType        #374:#384     // addServlet:(Ljava/lang/String;Ljava/lang/Class;)Lcom/github/netty/protocol/servlet/ServletRegistration;
  #603 = Utf8               java/lang/InstantiationException
  #604 = Utf8               java/lang/IllegalAccessException
  #605 = Utf8               java/lang/ClassNotFoundException
  #606 = Class              #666          // java/lang/ReflectiveOperationException
  #607 = NameAndType        #762:#670     // printStackTrace:()V
  #608 = NameAndType        #763:#764     // onServletAdded:(Ljavax/servlet/Servlet;)Ljavax/servlet/Servlet;
  #609 = NameAndType        #228:#765     // "<init>":(Ljava/lang/String;Ljavax/servlet/Servlet;Lcom/github/netty/protocol/servlet/ServletContext;Lcom/github/netty/protocol/servlet/util/UrlMapper;)V
  #610 = Utf8               javax/servlet/Servlet
  #611 = NameAndType        #374:#379     // addServlet:(Ljava/lang/String;Ljavax/servlet/Servlet;)Lcom/github/netty/protocol/servlet/ServletRegistration;
  #612 = NameAndType        #397:#405     // addFilter:(Ljava/lang/String;Ljava/lang/Class;)Lcom/github/netty/protocol/servlet/ServletFilterRegistration;
  #613 = NameAndType        #228:#766     // "<init>":(Ljava/lang/String;Ljavax/servlet/Filter;Lcom/github/netty/protocol/servlet/ServletContext;Lcom/github/netty/protocol/servlet/util/UrlMapper;)V
  #614 = Utf8               javax/servlet/Filter
  #615 = NameAndType        #397:#402     // addFilter:(Ljava/lang/String;Ljavax/servlet/Filter;)Lcom/github/netty/protocol/servlet/ServletFilterRegistration;
  #616 = Utf8               javax/servlet/FilterRegistration
  #617 = NameAndType        #219:#198     // sessionTrackingModeSet:Ljava/util/Set;
  #618 = NameAndType        #422:#423     // getDefaultSessionTrackingModes:()Ljava/util/Set;
  #619 = NameAndType        #426:#431     // addListener:(Ljava/lang/Class;)V
  #620 = Utf8               javax/servlet/ServletContextAttributeListener
  #621 = NameAndType        #767:#768     // addServletContextAttributeListener:(Ljavax/servlet/ServletContextAttributeListener;)V
  #622 = Utf8               javax/servlet/ServletRequestListener
  #623 = NameAndType        #769:#770     // addServletRequestListener:(Ljavax/servlet/ServletRequestListener;)V
  #624 = Utf8               javax/servlet/ServletRequestAttributeListener
  #625 = NameAndType        #771:#772     // addServletRequestAttributeListener:(Ljavax/servlet/ServletRequestAttributeListener;)V
  #626 = Utf8               javax/servlet/http/HttpSessionIdListener
  #627 = NameAndType        #773:#774     // addHttpSessionIdListenerListener:(Ljavax/servlet/http/HttpSessionIdListener;)V
  #628 = Utf8               javax/servlet/http/HttpSessionAttributeListener
  #629 = NameAndType        #775:#776     // addHttpSessionAttributeListener:(Ljavax/servlet/http/HttpSessionAttributeListener;)V
  #630 = Utf8               javax/servlet/http/HttpSessionListener
  #631 = NameAndType        #777:#778     // addHttpSessionListener:(Ljavax/servlet/http/HttpSessionListener;)V
  #632 = Utf8               javax/servlet/ServletContextListener
  #633 = NameAndType        #779:#780     // addServletContextListener:(Ljavax/servlet/ServletContextListener;)V
  #634 = Utf8               java/lang/IllegalArgumentException
  #635 = Utf8               applicationContext.addListener.iae.wrongType
  #636 = NameAndType        #228:#257     // "<init>":(Ljava/lang/String;)V
  #637 = Utf8               java/util/EventListener
  #638 = NameAndType        #426:#427     // addListener:(Ljava/util/EventListener;)V
  #639 = NameAndType        #440:#441     // getClassLoader:()Ljava/lang/ClassLoader;
  #640 = Utf8                (
  #641 = Utf8               :
  #642 = Utf8               user.name
  #643 = Class              #781          // com/github/netty/core/util/SystemPropertyUtil
  #644 = NameAndType        #223:#221     // requestCharacterEncoding:Ljava/lang/String;
  #645 = Class              #782          // com/github/netty/protocol/servlet/util/HttpConstants
  #646 = NameAndType        #783:#784     // DEFAULT_CHARSET:Ljava/nio/charset/Charset;
  #647 = Class              #785          // java/nio/charset/Charset
  #648 = NameAndType        #319:#260     // name:()Ljava/lang/String;
  #649 = NameAndType        #224:#221     // responseCharacterEncoding:Ljava/lang/String;
  #650 = NameAndType        #416:#417     // getSessionCookieConfig:()Lcom/github/netty/protocol/servlet/ServletSessionCookieConfig;
  #651 = NameAndType        #397:#398     // addFilter:(Ljava/lang/String;Ljava/lang/String;)Lcom/github/netty/protocol/servlet/ServletFilterRegistration;
  #652 = NameAndType        #374:#375     // addServlet:(Ljava/lang/String;Ljava/lang/String;)Lcom/github/netty/protocol/servlet/ServletRegistration;
  #653 = NameAndType        #315:#307     // getNamedDispatcher:(Ljava/lang/String;)Lcom/github/netty/protocol/servlet/ServletRequestDispatcher;
  #654 = NameAndType        #306:#307     // getRequestDispatcher:(Ljava/lang/String;)Lcom/github/netty/protocol/servlet/ServletRequestDispatcher;
  #655 = NameAndType        #283:#284     // getContext:(Ljava/lang/String;)Lcom/github/netty/protocol/servlet/ServletContext;
  #656 = Utf8               com/github/netty/protocol/servlet/ServletContext
  #657 = Utf8               java/lang/Object
  #658 = Utf8               javax/servlet/ServletContext
  #659 = Utf8               java/lang/ClassLoader
  #660 = Utf8               java/lang/Throwable
  #661 = Utf8               java/net/MalformedURLException
  #662 = Utf8               com/github/netty/protocol/servlet/ServletFilterChain
  #663 = Utf8               java/util/List
  #664 = Utf8               java/util/Iterator
  #665 = Utf8               javax/servlet/ServletException
  #666 = Utf8               java/lang/ReflectiveOperationException
  #667 = Class              #786          // javax/servlet/ServletRegistration
  #668 = Utf8               javax/servlet/ServletRegistration$Dynamic
  #669 = Utf8               javax/servlet/FilterRegistration$Dynamic
  #670 = Utf8               ()V
  #671 = Utf8               getClass
  #672 = Utf8               ()Ljava/lang/Class;
  #673 = Utf8               com/github/netty/core/util/LoggerFactoryX
  #674 = Utf8               getLogger
  #675 = Utf8               (Ljava/lang/Class;)Lcom/github/netty/core/util/LoggerX;
  #676 = Utf8               COOKIE
  #677 = Utf8               Ljavax/servlet/SessionTrackingMode;
  #678 = Utf8               URL
  #679 = Utf8               java/util/Arrays
  #680 = Utf8               asList
  #681 = Utf8               ([Ljava/lang/Object;)Ljava/util/List;
  #682 = Utf8               (Ljava/util/Collection;)V
  #683 = Utf8               (Z)V
  #684 = Utf8               java/util/Objects
  #685 = Utf8               requireNonNull
  #686 = Utf8               (Ljava/lang/Object;)Ljava/lang/Object;
  #687 = Utf8               append
  #688 = Utf8               (C)Ljava/lang/StringBuilder;
  #689 = Utf8               getHostName
  #690 = Utf8               com/github/netty/core/util/HostUtil
  #691 = Utf8               isLocalhost
  #692 = Utf8               (Ljava/lang/String;)Z
  #693 = Utf8               (Ljava/lang/String;)Ljava/lang/StringBuilder;
  #694 = Utf8               toString
  #695 = Utf8               (Ljava/lang/String;Ljava/lang/String;Ljava/lang/ClassLoader;)V
  #696 = Utf8               mkdirs
  #697 = Utf8               (Ljava/lang/String;I)V
  #698 = Utf8               java/lang/Long
  #699 = Utf8               parseLong
  #700 = Utf8               (Ljava/lang/String;)J
  #701 = Utf8               lastIndexOf
  #702 = Utf8               (I)I
  #703 = Utf8               substring
  #704 = Utf8               (I)Ljava/lang/String;
  #705 = Utf8               length
  #706 = Utf8               get
  #707 = Utf8               getMappingObjectByUri
  #708 = Utf8               newInstance
  #709 = Utf8               (Lcom/github/netty/protocol/servlet/ServletContext;Lcom/github/netty/protocol/servlet/ServletRegistration;)Lcom/github/netty/protocol/servlet/ServletFilterChain;
  #710 = Utf8               getFilterRegistrationList
  #711 = Utf8               ()Ljava/util/List;
  #712 = Utf8               getMappingObjectsByUri
  #713 = Utf8               (Ljava/lang/String;Ljava/util/List;)Ljava/util/List;
  #714 = Utf8               com/github/netty/protocol/servlet/ServletRequestDispatcher
  #715 = Utf8               (Lcom/github/netty/protocol/servlet/ServletFilterChain;)Lcom/github/netty/protocol/servlet/ServletRequestDispatcher;
  #716 = Utf8               setPath
  #717 = Utf8               java/util/Map
  #718 = Utf8               values
  #719 = Utf8               ()Ljava/util/Collection;
  #720 = Utf8               java/util/Collection
  #721 = Utf8               iterator
  #722 = Utf8               ()Ljava/util/Iterator;
  #723 = Utf8               hasNext
  #724 = Utf8               ()Z
  #725 = Utf8               next
  #726 = Utf8               ()Ljava/lang/Object;
  #727 = Utf8               getServletNameMappings
  #728 = Utf8               equals
  #729 = Utf8               (Ljava/lang/Object;)Z
  #730 = Utf8               add
  #731 = Utf8               setName
  #732 = Utf8               ()Ljavax/servlet/Servlet;
  #733 = Utf8               java/util/Collections
  #734 = Utf8               enumeration
  #735 = Utf8               (Ljava/util/Collection;)Ljava/util/Enumeration;
  #736 = Utf8               getName
  #737 = Utf8               com/github/netty/core/util/LoggerX
  #738 = Utf8               debug
  #739 = Utf8               com/github/netty/protocol/servlet/util/ServletUtil
  #740 = Utf8               concat
  #741 = Utf8               getJvmVersion
  #742 = Utf8               getOsName
  #743 = Utf8               getArch
  #744 = Utf8               com/github/netty/core/util/TypeUtil
  #745 = Utf8               cast
  #746 = Utf8               (Ljava/lang/Object;Ljava/lang/Class;)Ljava/lang/Object;
  #747 = Utf8               isAssignableFrom
  #748 = Utf8               (Ljava/lang/Class;)Z
  #749 = Utf8               keySet
  #750 = Utf8               putIfAbsent
  #751 = Utf8               (Ljava/lang/Object;Ljava/lang/Object;)Ljava/lang/Object;
  #752 = Utf8               put
  #753 = Utf8               hasServletContextAttributeListener
  #754 = Utf8               (Ljavax/servlet/ServletContext;Ljava/lang/String;Ljava/lang/Object;)V
  #755 = Utf8               onServletContextAttributeAdded
  #756 = Utf8               (Ljavax/servlet/ServletContextAttributeEvent;)V
  #757 = Utf8               onServletContextAttributeReplaced
  #758 = Utf8               remove
  #759 = Utf8               onServletContextAttributeRemoved
  #760 = Utf8               forName
  #761 = Utf8               (Ljava/lang/String;)Ljava/lang/Class;
  #762 = Utf8               printStackTrace
  #763 = Utf8               onServletAdded
  #764 = Utf8               (Ljavax/servlet/Servlet;)Ljavax/servlet/Servlet;
  #765 = Utf8               (Ljava/lang/String;Ljavax/servlet/Servlet;Lcom/github/netty/protocol/servlet/ServletContext;Lcom/github/netty/protocol/servlet/util/UrlMapper;)V
  #766 = Utf8               (Ljava/lang/String;Ljavax/servlet/Filter;Lcom/github/netty/protocol/servlet/ServletContext;Lcom/github/netty/protocol/servlet/util/UrlMapper;)V
  #767 = Utf8               addServletContextAttributeListener
  #768 = Utf8               (Ljavax/servlet/ServletContextAttributeListener;)V
  #769 = Utf8               addServletRequestListener
  #770 = Utf8               (Ljavax/servlet/ServletRequestListener;)V
  #771 = Utf8               addServletRequestAttributeListener
  #772 = Utf8               (Ljavax/servlet/ServletRequestAttributeListener;)V
  #773 = Utf8               addHttpSessionIdListenerListener
  #774 = Utf8               (Ljavax/servlet/http/HttpSessionIdListener;)V
  #775 = Utf8               addHttpSessionAttributeListener
  #776 = Utf8               (Ljavax/servlet/http/HttpSessionAttributeListener;)V
  #777 = Utf8               addHttpSessionListener
  #778 = Utf8               (Ljavax/servlet/http/HttpSessionListener;)V
  #779 = Utf8               addServletContextListener
  #780 = Utf8               (Ljavax/servlet/ServletContextListener;)V
  #781 = Utf8               com/github/netty/core/util/SystemPropertyUtil
  #782 = Utf8               com/github/netty/protocol/servlet/util/HttpConstants
  #783 = Utf8               DEFAULT_CHARSET
  #784 = Utf8               Ljava/nio/charset/Charset;
  #785 = Utf8               java/nio/charset/Charset
  #786 = Utf8               javax/servlet/ServletRegistration
{
  public com.github.netty.protocol.servlet.ServletContext(java.net.InetSocketAddress, java.lang.ClassLoader, java.lang.String);
    descriptor: (Ljava/net/InetSocketAddress;Ljava/lang/ClassLoader;Ljava/lang/String;)V
    flags: ACC_PUBLIC
    Code:
      stack=7, locals=5, args_size=4
         0: aload_0
         1: invokespecial #1                  // Method java/lang/Object."<init>":()V
         4: aload_0
         5: aload_0
         6: invokevirtual #2                  // Method java/lang/Object.getClass:()Ljava/lang/Class;
         9: invokestatic  #3                  // Method com/github/netty/core/util/LoggerFactoryX.getLogger:(Ljava/lang/Class;)Lcom/github/netty/core/util/LoggerX;
        12: putfield      #4                  // Field logger:Lcom/github/netty/core/util/LoggerX;
        15: aload_0
        16: sipush        1200
        19: putfield      #5                  // Field sessionTimeout:I
        22: aload_0
        23: sipush        4096
        26: putfield      #6                  // Field responseWriterChunkMaxHeapByteLength:I
        29: aload_0
        30: new           #7                  // class java/util/HashMap
        33: dup
        34: bipush        16
        36: invokespecial #8                  // Method java/util/HashMap."<init>":(I)V
        39: putfield      #9                  // Field attributeMap:Ljava/util/Map;
        42: aload_0
        43: new           #7                  // class java/util/HashMap
        46: dup
        47: bipush        16
        49: invokespecial #8                  // Method java/util/HashMap."<init>":(I)V
        52: putfield      #10                 // Field initParamMap:Ljava/util/Map;
        55: aload_0
        56: new           #7                  // class java/util/HashMap
        59: dup
        60: bipush        8
        62: invokespecial #8                  // Method java/util/HashMap."<init>":(I)V
        65: putfield      #11                 // Field servletRegistrationMap:Ljava/util/Map;
        68: aload_0
        69: new           #7                  // class java/util/HashMap
        72: dup
        73: bipush        8
        75: invokespecial #8                  // Method java/util/HashMap."<init>":(I)V
        78: putfield      #12                 // Field filterRegistrationMap:Ljava/util/Map;
        81: aload_0
        82: new           #13                 // class java/util/HashSet
        85: dup
        86: iconst_2
        87: anewarray     #14                 // class javax/servlet/SessionTrackingMode
        90: dup
        91: iconst_0
        92: getstatic     #15                 // Field javax/servlet/SessionTrackingMode.COOKIE:Ljavax/servlet/SessionTrackingMode;
        95: aastore
        96: dup
        97: iconst_1
        98: getstatic     #16                 // Field javax/servlet/SessionTrackingMode.URL:Ljavax/servlet/SessionTrackingMode;
       101: aastore
       102: invokestatic  #17                 // Method java/util/Arrays.asList:([Ljava/lang/Object;)Ljava/util/List;
       105: invokespecial #18                 // Method java/util/HashSet."<init>":(Ljava/util/Collection;)V
       108: putfield      #19                 // Field defaultSessionTrackingModeSet:Ljava/util/Set;
       111: aload_0
       112: new           #20                 // class com/github/netty/protocol/servlet/ServletErrorPageManager
       115: dup
       116: invokespecial #21                 // Method com/github/netty/protocol/servlet/ServletErrorPageManager."<init>":()V
       119: putfield      #22                 // Field servletErrorPageManager:Lcom/github/netty/protocol/servlet/ServletErrorPageManager;
       122: aload_0
       123: new           #23                 // class com/github/netty/protocol/servlet/util/MimeMappingsX
       126: dup
       127: invokespecial #24                 // Method com/github/netty/protocol/servlet/util/MimeMappingsX."<init>":()V
       130: putfield      #25                 // Field mimeMappings:Lcom/github/netty/protocol/servlet/util/MimeMappingsX;
       133: aload_0
       134: new           #26                 // class com/github/netty/protocol/servlet/ServletEventListenerManager
       137: dup
       138: invokespecial #27                 // Method com/github/netty/protocol/servlet/ServletEventListenerManager."<init>":()V
       141: putfield      #28                 // Field servletEventListenerManager:Lcom/github/netty/protocol/servlet/ServletEventListenerManager;
       144: aload_0
       145: new           #29                 // class com/github/netty/protocol/servlet/ServletSessionCookieConfig
       148: dup
       149: invokespecial #30                 // Method com/github/netty/protocol/servlet/ServletSessionCookieConfig."<init>":()V
       152: putfield      #31                 // Field sessionCookieConfig:Lcom/github/netty/protocol/servlet/ServletSessionCookieConfig;
       155: aload_0
       156: new           #32                 // class com/github/netty/protocol/servlet/util/UrlMapper
       159: dup
       160: iconst_1
       161: invokespecial #33                 // Method com/github/netty/protocol/servlet/util/UrlMapper."<init>":(Z)V
       164: putfield      #34                 // Field servletUrlMapper:Lcom/github/netty/protocol/servlet/util/UrlMapper;
       167: aload_0
       168: new           #32                 // class com/github/netty/protocol/servlet/util/UrlMapper
       171: dup
       172: iconst_0
       173: invokespecial #33                 // Method com/github/netty/protocol/servlet/util/UrlMapper."<init>":(Z)V
       176: putfield      #35                 // Field filterUrlMapper:Lcom/github/netty/protocol/servlet/util/UrlMapper;
       179: aload_0
       180: aload_1
       181: invokestatic  #36                 // Method java/util/Objects.requireNonNull:(Ljava/lang/Object;)Ljava/lang/Object;
       184: checkcast     #37                 // class java/net/InetSocketAddress
       187: putfield      #38                 // Field servletServerAddress:Ljava/net/InetSocketAddress;
       190: new           #39                 // class java/lang/StringBuilder
       193: dup
       194: invokespecial #40                 // Method java/lang/StringBuilder."<init>":()V
       197: bipush        47
       199: invokevirtual #41                 // Method java/lang/StringBuilder.append:(C)Ljava/lang/StringBuilder;
       202: aload_1
       203: invokevirtual #42                 // Method java/net/InetSocketAddress.getHostName:()Ljava/lang/String;
       206: invokestatic  #43                 // Method com/github/netty/core/util/HostUtil.isLocalhost:(Ljava/lang/String;)Z
       209: ifeq          217
       212: ldc           #44                 // String localhost
       214: goto          221
       217: aload_1
       218: invokevirtual #42                 // Method java/net/InetSocketAddress.getHostName:()Ljava/lang/String;
       221: invokevirtual #45                 // Method java/lang/StringBuilder.append:(Ljava/lang/String;)Ljava/lang/StringBuilder;
       224: invokevirtual #46                 // Method java/lang/StringBuilder.toString:()Ljava/lang/String;
       227: astore        4
       229: aload_0
       230: new           #47                 // class com/github/netty/core/util/ResourceManager
       233: dup
       234: aload_3
       235: aload         4
       237: aload_2
       238: invokespecial #48                 // Method com/github/netty/core/util/ResourceManager."<init>":(Ljava/lang/String;Ljava/lang/String;Ljava/lang/ClassLoader;)V
       241: putfield      #49                 // Field resourceManager:Lcom/github/netty/core/util/ResourceManager;
       244: aload_0
       245: getfield      #49                 // Field resourceManager:Lcom/github/netty/core/util/ResourceManager;
       248: ldc           #50                 // String /
       250: invokevirtual #51                 // Method com/github/netty/core/util/ResourceManager.mkdirs:(Ljava/lang/String;)Z
       253: pop
       254: return
      LineNumberTable:
        line 62: 0
        line 27: 4
        line 31: 15
        line 35: 22
        line 36: 29
        line 37: 42
        line 38: 55
        line 39: 68
        line 40: 81
        line 43: 111
        line 44: 122
        line 45: 133
        line 46: 144
        line 47: 155
        line 48: 167
        line 63: 179
        line 64: 190
        line 65: 229
        line 66: 244
        line 67: 254
      LocalVariableTable:
        Start  Length  Slot  Name   Signature
            0     255     0  this   Lcom/github/netty/protocol/servlet/ServletContext;
            0     255     1 socketAddress   Ljava/net/InetSocketAddress;
            0     255     2 classLoader   Ljava/lang/ClassLoader;
            0     255     3 docBase   Ljava/lang/String;
          229      26     4 workspace   Ljava/lang/String;
      StackMapTable: number_of_entries = 2
        frame_type = 255 /* full_frame */
          offset_delta = 217
          locals = [ class com/github/netty/protocol/servlet/ServletContext, class java/net/InetSocketAddress, class java/lang/ClassLoader, class java/lang/String ]
          stack = [ class java/lang/StringBuilder ]
        frame_type = 255 /* full_frame */
          offset_delta = 3
          locals = [ class com/github/netty/protocol/servlet/ServletContext, class java/net/InetSocketAddress, class java/lang/ClassLoader, class java/lang/String ]
          stack = [ class java/lang/StringBuilder, class java/lang/String ]

  public java.util.concurrent.ExecutorService getAsyncExecutorService();
    descriptor: ()Ljava/util/concurrent/ExecutorService;
    flags: ACC_PUBLIC
    Code:
      stack=5, locals=3, args_size=1
         0: aload_0
         1: getfield      #52                 // Field asyncExecutorService:Ljava/util/concurrent/ExecutorService;
         4: ifnonnull     43
         7: aload_0
         8: dup
         9: astore_1
        10: monitorenter
        11: aload_0
        12: getfield      #52                 // Field asyncExecutorService:Ljava/util/concurrent/ExecutorService;
        15: ifnonnull     33
        18: aload_0
        19: new           #53                 // class com/github/netty/core/util/ThreadPoolX
        22: dup
        23: ldc           #54                 // String Async
        25: bipush        8
        27: invokespecial #55                 // Method com/github/netty/core/util/ThreadPoolX."<init>":(Ljava/lang/String;I)V
        30: putfield      #52                 // Field asyncExecutorService:Ljava/util/concurrent/ExecutorService;
        33: aload_1
        34: monitorexit
        35: goto          43
        38: astore_2
        39: aload_1
        40: monitorexit
        41: aload_2
        42: athrow
        43: aload_0
        44: getfield      #52                 // Field asyncExecutorService:Ljava/util/concurrent/ExecutorService;
        47: areturn
      Exception table:
         from    to  target type
            11    35    38   any
            38    41    38   any
      LineNumberTable:
        line 70: 0
        line 71: 7
        line 72: 11
        line 73: 18
        line 76: 33
        line 78: 43
      LocalVariableTable:
        Start  Length  Slot  Name   Signature
            0      48     0  this   Lcom/github/netty/protocol/servlet/ServletContext;
      StackMapTable: number_of_entries = 3
        frame_type = 252 /* append */
          offset_delta = 33
          locals = [ class java/lang/Object ]
        frame_type = 68 /* same_locals_1_stack_item */
          stack = [ class java/lang/Throwable ]
        frame_type = 250 /* chop */
          offset_delta = 4

  public com.github.netty.protocol.servlet.util.MimeMappingsX getMimeMappings();
    descriptor: ()Lcom/github/netty/protocol/servlet/util/MimeMappingsX;
    flags: ACC_PUBLIC
    Code:
      stack=1, locals=1, args_size=1
         0: aload_0
         1: getfield      #25                 // Field mimeMappings:Lcom/github/netty/protocol/servlet/util/MimeMappingsX;
         4: areturn
      LineNumberTable:
        line 82: 0
      LocalVariableTable:
        Start  Length  Slot  Name   Signature
            0       5     0  this   Lcom/github/netty/protocol/servlet/ServletContext;

  public com.github.netty.core.util.ResourceManager getResourceManager();
    descriptor: ()Lcom/github/netty/core/util/ResourceManager;
    flags: ACC_PUBLIC
    Code:
      stack=1, locals=1, args_size=1
         0: aload_0
         1: getfield      #49                 // Field resourceManager:Lcom/github/netty/core/util/ResourceManager;
         4: areturn
      LineNumberTable:
        line 86: 0
      LocalVariableTable:
        Start  Length  Slot  Name   Signature
            0       5     0  this   Lcom/github/netty/protocol/servlet/ServletContext;

  public com.github.netty.protocol.servlet.ServletErrorPageManager getErrorPageManager();
    descriptor: ()Lcom/github/netty/protocol/servlet/ServletErrorPageManager;
    flags: ACC_PUBLIC
    Code:
      stack=1, locals=1, args_size=1
         0: aload_0
         1: getfield      #22                 // Field servletErrorPageManager:Lcom/github/netty/protocol/servlet/ServletErrorPageManager;
         4: areturn
      LineNumberTable:
        line 90: 0
      LocalVariableTable:
        Start  Length  Slot  Name   Signature
            0       5     0  this   Lcom/github/netty/protocol/servlet/ServletContext;

  public void setServletContextName(java.lang.String);
    descriptor: (Ljava/lang/String;)V
    flags: ACC_PUBLIC
    Code:
      stack=2, locals=2, args_size=2
         0: aload_0
         1: aload_1
         2: putfield      #56                 // Field servletContextName:Ljava/lang/String;
         5: return
      LineNumberTable:
        line 94: 0
        line 95: 5
      LocalVariableTable:
        Start  Length  Slot  Name   Signature
            0       6     0  this   Lcom/github/netty/protocol/servlet/ServletContext;
            0       6     1 servletContextName   Ljava/lang/String;

  public void setServerHeader(java.lang.String);
    descriptor: (Ljava/lang/String;)V
    flags: ACC_PUBLIC
    Code:
      stack=2, locals=2, args_size=2
         0: aload_0
         1: aload_1
         2: putfield      #57                 // Field serverHeader:Ljava/lang/String;
         5: return
      LineNumberTable:
        line 98: 0
        line 99: 5
      LocalVariableTable:
        Start  Length  Slot  Name   Signature
            0       6     0  this   Lcom/github/netty/protocol/servlet/ServletContext;
            0       6     1 serverHeader   Ljava/lang/String;

  public java.lang.String getServerHeader();
    descriptor: ()Ljava/lang/String;
    flags: ACC_PUBLIC
    Code:
      stack=1, locals=1, args_size=1
         0: aload_0
         1: getfield      #57                 // Field serverHeader:Ljava/lang/String;
         4: areturn
      LineNumberTable:
        line 102: 0
      LocalVariableTable:
        Start  Length  Slot  Name   Signature
            0       5     0  this   Lcom/github/netty/protocol/servlet/ServletContext;

  public void setContextPath(java.lang.String);
    descriptor: (Ljava/lang/String;)V
    flags: ACC_PUBLIC
    Code:
      stack=2, locals=2, args_size=2
         0: aload_0
         1: aload_1
         2: putfield      #58                 // Field contextPath:Ljava/lang/String;
         5: return
      LineNumberTable:
        line 106: 0
        line 107: 5
      LocalVariableTable:
        Start  Length  Slot  Name   Signature
            0       6     0  this   Lcom/github/netty/protocol/servlet/ServletContext;
            0       6     1 contextPath   Ljava/lang/String;

  public com.github.netty.protocol.servlet.ServletEventListenerManager getServletEventListenerManager();
    descriptor: ()Lcom/github/netty/protocol/servlet/ServletEventListenerManager;
    flags: ACC_PUBLIC
    Code:
      stack=1, locals=1, args_size=1
         0: aload_0
         1: getfield      #28                 // Field servletEventListenerManager:Lcom/github/netty/protocol/servlet/ServletEventListenerManager;
         4: areturn
      LineNumberTable:
        line 110: 0
      LocalVariableTable:
        Start  Length  Slot  Name   Signature
            0       5     0  this   Lcom/github/netty/protocol/servlet/ServletContext;

  public long getAsyncTimeout();
    descriptor: ()J
    flags: ACC_PUBLIC
    Code:
      stack=2, locals=3, args_size=1
         0: aload_0
         1: ldc           #59                 // String asyncTimeout
         3: invokevirtual #60                 // Method getInitParameter:(Ljava/lang/String;)Ljava/lang/String;
         6: astore_1
         7: aload_1
         8: ifnonnull     15
        11: ldc2_w        #61                 // long 10000l
        14: lreturn
        15: aload_1
        16: invokestatic  #63                 // Method java/lang/Long.parseLong:(Ljava/lang/String;)J
        19: lreturn
        20: astore_2
        21: ldc2_w        #61                 // long 10000l
        24: lreturn
      Exception table:
         from    to  target type
            15    19    20   Class java/lang/NumberFormatException
      LineNumberTable:
        line 114: 0
        line 115: 7
        line 116: 11
        line 119: 15
        line 120: 20
        line 121: 21
      LocalVariableTable:
        Start  Length  Slot  Name   Signature
           21       4     2     e   Ljava/lang/NumberFormatException;
            0      25     0  this   Lcom/github/netty/protocol/servlet/ServletContext;
            7      18     1 value   Ljava/lang/String;
      StackMapTable: number_of_entries = 2
        frame_type = 252 /* append */
          offset_delta = 15
          locals = [ class java/lang/String ]
        frame_type = 68 /* same_locals_1_stack_item */
          stack = [ class java/lang/NumberFormatException ]

  public int getResponseWriterChunkMaxHeapByteLength();
    descriptor: ()I
    flags: ACC_PUBLIC
    Code:
      stack=1, locals=1, args_size=1
         0: aload_0
         1: getfield      #6                  // Field responseWriterChunkMaxHeapByteLength:I
         4: ireturn
      LineNumberTable:
        line 126: 0
      LocalVariableTable:
        Start  Length  Slot  Name   Signature
            0       5     0  this   Lcom/github/netty/protocol/servlet/ServletContext;

  public void setResponseWriterChunkMaxHeapByteLength(int);
    descriptor: (I)V
    flags: ACC_PUBLIC
    Code:
      stack=2, locals=2, args_size=2
         0: aload_0
         1: iload_1
         2: putfield      #6                  // Field responseWriterChunkMaxHeapByteLength:I
         5: return
      LineNumberTable:
        line 130: 0
        line 131: 5
      LocalVariableTable:
        Start  Length  Slot  Name   Signature
            0       6     0  this   Lcom/github/netty/protocol/servlet/ServletContext;
            0       6     1 responseWriterChunkMaxHeapByteLength   I

  public java.net.InetSocketAddress getServletServerAddress();
    descriptor: ()Ljava/net/InetSocketAddress;
    flags: ACC_PUBLIC
    Code:
      stack=1, locals=1, args_size=1
         0: aload_0
         1: getfield      #38                 // Field servletServerAddress:Ljava/net/InetSocketAddress;
         4: areturn
      LineNumberTable:
        line 134: 0
      LocalVariableTable:
        Start  Length  Slot  Name   Signature
            0       5     0  this   Lcom/github/netty/protocol/servlet/ServletContext;

  public void setSessionService(com.github.netty.protocol.servlet.SessionService);
    descriptor: (Lcom/github/netty/protocol/servlet/SessionService;)V
    flags: ACC_PUBLIC
    Code:
      stack=2, locals=2, args_size=2
         0: aload_0
         1: aload_1
         2: putfield      #65                 // Field sessionService:Lcom/github/netty/protocol/servlet/SessionService;
         5: return
      LineNumberTable:
        line 138: 0
        line 139: 5
      LocalVariableTable:
        Start  Length  Slot  Name   Signature
            0       6     0  this   Lcom/github/netty/protocol/servlet/ServletContext;
            0       6     1 sessionService   Lcom/github/netty/protocol/servlet/SessionService;

  public com.github.netty.protocol.servlet.SessionService getSessionService();
    descriptor: ()Lcom/github/netty/protocol/servlet/SessionService;
    flags: ACC_PUBLIC
    Code:
      stack=1, locals=1, args_size=1
         0: aload_0
         1: getfield      #65                 // Field sessionService:Lcom/github/netty/protocol/servlet/SessionService;
         4: areturn
      LineNumberTable:
        line 142: 0
      LocalVariableTable:
        Start  Length  Slot  Name   Signature
            0       5     0  this   Lcom/github/netty/protocol/servlet/ServletContext;

  public int getSessionTimeout();
    descriptor: ()I
    flags: ACC_PUBLIC
    Code:
      stack=1, locals=1, args_size=1
         0: aload_0
         1: getfield      #5                  // Field sessionTimeout:I
         4: ireturn
      LineNumberTable:
        line 146: 0
      LocalVariableTable:
        Start  Length  Slot  Name   Signature
            0       5     0  this   Lcom/github/netty/protocol/servlet/ServletContext;

  public void setSessionTimeout(int);
    descriptor: (I)V
    flags: ACC_PUBLIC
    Code:
      stack=2, locals=2, args_size=2
         0: iload_1
         1: ifgt          5
         4: return
         5: aload_0
         6: iload_1
         7: putfield      #5                  // Field sessionTimeout:I
        10: return
      LineNumberTable:
        line 150: 0
        line 151: 4
        line 153: 5
        line 154: 10
      LocalVariableTable:
        Start  Length  Slot  Name   Signature
            0      11     0  this   Lcom/github/netty/protocol/servlet/ServletContext;
            0      11     1 sessionTimeout   I
      StackMapTable: number_of_entries = 1
        frame_type = 5 /* same */

  public java.lang.String getContextPath();
    descriptor: ()Ljava/lang/String;
    flags: ACC_PUBLIC
    Code:
      stack=1, locals=1, args_size=1
         0: aload_0
         1: getfield      #58                 // Field contextPath:Ljava/lang/String;
         4: areturn
      LineNumberTable:
        line 158: 0
      LocalVariableTable:
        Start  Length  Slot  Name   Signature
            0       5     0  this   Lcom/github/netty/protocol/servlet/ServletContext;

  public com.github.netty.protocol.servlet.ServletContext getContext(java.lang.String);
    descriptor: (Ljava/lang/String;)Lcom/github/netty/protocol/servlet/ServletContext;
    flags: ACC_PUBLIC
    Code:
      stack=1, locals=2, args_size=2
         0: aload_0
         1: areturn
      LineNumberTable:
        line 163: 0
      LocalVariableTable:
        Start  Length  Slot  Name   Signature
            0       2     0  this   Lcom/github/netty/protocol/servlet/ServletContext;
            0       2     1 uripath   Ljava/lang/String;

  public int getMajorVersion();
    descriptor: ()I
    flags: ACC_PUBLIC
    Code:
      stack=1, locals=1, args_size=1
         0: iconst_3
         1: ireturn
      LineNumberTable:
        line 168: 0
      LocalVariableTable:
        Start  Length  Slot  Name   Signature
            0       2     0  this   Lcom/github/netty/protocol/servlet/ServletContext;

  public int getMinorVersion();
    descriptor: ()I
    flags: ACC_PUBLIC
    Code:
      stack=1, locals=1, args_size=1
         0: iconst_0
         1: ireturn
      LineNumberTable:
        line 173: 0
      LocalVariableTable:
        Start  Length  Slot  Name   Signature
            0       2     0  this   Lcom/github/netty/protocol/servlet/ServletContext;

  public int getEffectiveMajorVersion();
    descriptor: ()I
    flags: ACC_PUBLIC
    Code:
      stack=1, locals=1, args_size=1
         0: iconst_3
         1: ireturn
      LineNumberTable:
        line 178: 0
      LocalVariableTable:
        Start  Length  Slot  Name   Signature
            0       2     0  this   Lcom/github/netty/protocol/servlet/ServletContext;

  public int getEffectiveMinorVersion();
    descriptor: ()I
    flags: ACC_PUBLIC
    Code:
      stack=1, locals=1, args_size=1
         0: iconst_0
         1: ireturn
      LineNumberTable:
        line 183: 0
      LocalVariableTable:
        Start  Length  Slot  Name   Signature
            0       2     0  this   Lcom/github/netty/protocol/servlet/ServletContext;

  public java.lang.String getMimeType(java.lang.String);
    descriptor: (Ljava/lang/String;)Ljava/lang/String;
    flags: ACC_PUBLIC
    Code:
      stack=3, locals=4, args_size=2
         0: aload_1
         1: ifnonnull     6
         4: aconst_null
         5: areturn
         6: aload_1
         7: bipush        46
         9: invokevirtual #66                 // Method java/lang/String.lastIndexOf:(I)I
        12: istore_2
        13: iload_2
        14: ifge          19
        17: aconst_null
        18: areturn
        19: aload_1
        20: iload_2
        21: iconst_1
        22: iadd
        23: invokevirtual #67                 // Method java/lang/String.substring:(I)Ljava/lang/String;
        26: astore_3
        27: aload_3
        28: invokevirtual #68                 // Method java/lang/String.length:()I
        31: iconst_1
        32: if_icmpge     37
        35: aconst_null
        36: areturn
        37: aload_0
        38: getfield      #25                 // Field mimeMappings:Lcom/github/netty/protocol/servlet/util/MimeMappingsX;
        41: aload_3
        42: invokevirtual #69                 // Method com/github/netty/protocol/servlet/util/MimeMappingsX.get:(Ljava/lang/String;)Ljava/lang/String;
        45: areturn
      LineNumberTable:
        line 188: 0
        line 189: 4
        line 191: 6
        line 192: 13
        line 193: 17
        line 195: 19
        line 196: 27
        line 197: 35
        line 199: 37
      LocalVariableTable:
        Start  Length  Slot  Name   Signature
            0      46     0  this   Lcom/github/netty/protocol/servlet/ServletContext;
            0      46     1  file   Ljava/lang/String;
           13      33     2 period   I
           27      19     3 extension   Ljava/lang/String;
      StackMapTable: number_of_entries = 3
        frame_type = 6 /* same */
        frame_type = 252 /* append */
          offset_delta = 12
          locals = [ int ]
        frame_type = 252 /* append */
          offset_delta = 17
          locals = [ class java/lang/String ]

  public java.util.Set<java.lang.String> getResourcePaths(java.lang.String);
    descriptor: (Ljava/lang/String;)Ljava/util/Set;
    flags: ACC_PUBLIC
    Code:
      stack=2, locals=2, args_size=2
         0: aload_0
         1: getfield      #49                 // Field resourceManager:Lcom/github/netty/core/util/ResourceManager;
         4: aload_1
         5: invokevirtual #70                 // Method com/github/netty/core/util/ResourceManager.getResourcePaths:(Ljava/lang/String;)Ljava/util/Set;
         8: areturn
      LineNumberTable:
        line 204: 0
      LocalVariableTable:
        Start  Length  Slot  Name   Signature
            0       9     0  this   Lcom/github/netty/protocol/servlet/ServletContext;
            0       9     1  path   Ljava/lang/String;
    Signature: #298                         // (Ljava/lang/String;)Ljava/util/Set<Ljava/lang/String;>;

  public java.net.URL getResource(java.lang.String) throws java.net.MalformedURLException;
    descriptor: (Ljava/lang/String;)Ljava/net/URL;
    flags: ACC_PUBLIC
    Code:
      stack=2, locals=2, args_size=2
         0: aload_0
         1: getfield      #49                 // Field resourceManager:Lcom/github/netty/core/util/ResourceManager;
         4: aload_1
         5: invokevirtual #71                 // Method com/github/netty/core/util/ResourceManager.getResource:(Ljava/lang/String;)Ljava/net/URL;
         8: areturn
      LineNumberTable:
        line 209: 0
      LocalVariableTable:
        Start  Length  Slot  Name   Signature
            0       9     0  this   Lcom/github/netty/protocol/servlet/ServletContext;
            0       9     1  path   Ljava/lang/String;
    Exceptions:
      throws java.net.MalformedURLException

  public java.io.InputStream getResourceAsStream(java.lang.String);
    descriptor: (Ljava/lang/String;)Ljava/io/InputStream;
    flags: ACC_PUBLIC
    Code:
      stack=2, locals=2, args_size=2
         0: aload_0
         1: getfield      #49                 // Field resourceManager:Lcom/github/netty/core/util/ResourceManager;
         4: aload_1
         5: invokevirtual #72                 // Method com/github/netty/core/util/ResourceManager.getResourceAsStream:(Ljava/lang/String;)Ljava/io/InputStream;
         8: areturn
      LineNumberTable:
        line 214: 0
      LocalVariableTable:
        Start  Length  Slot  Name   Signature
            0       9     0  this   Lcom/github/netty/protocol/servlet/ServletContext;
            0       9     1  path   Ljava/lang/String;

  public java.lang.String getRealPath(java.lang.String);
    descriptor: (Ljava/lang/String;)Ljava/lang/String;
    flags: ACC_PUBLIC
    Code:
      stack=2, locals=2, args_size=2
         0: aload_0
         1: getfield      #49                 // Field resourceManager:Lcom/github/netty/core/util/ResourceManager;
         4: aload_1
         5: invokevirtual #73                 // Method com/github/netty/core/util/ResourceManager.getRealPath:(Ljava/lang/String;)Ljava/lang/String;
         8: areturn
      LineNumberTable:
        line 219: 0
      LocalVariableTable:
        Start  Length  Slot  Name   Signature
            0       9     0  this   Lcom/github/netty/protocol/servlet/ServletContext;
            0       9     1  path   Ljava/lang/String;

  public com.github.netty.protocol.servlet.ServletRequestDispatcher getRequestDispatcher(java.lang.String);
    descriptor: (Ljava/lang/String;)Lcom/github/netty/protocol/servlet/ServletRequestDispatcher;
    flags: ACC_PUBLIC
    Code:
      stack=3, locals=5, args_size=2
         0: aload_0
         1: getfield      #34                 // Field servletUrlMapper:Lcom/github/netty/protocol/servlet/util/UrlMapper;
         4: aload_1
         5: invokevirtual #74                 // Method com/github/netty/protocol/servlet/util/UrlMapper.getMappingObjectByUri:(Ljava/lang/String;)Ljava/lang/Object;
         8: checkcast     #75                 // class com/github/netty/protocol/servlet/ServletRegistration
        11: astore_2
        12: aload_2
        13: ifnonnull     18
        16: aconst_null
        17: areturn
        18: aload_0
        19: aload_2
        20: invokestatic  #76                 // Method com/github/netty/protocol/servlet/ServletFilterChain.newInstance:(Lcom/github/netty/protocol/servlet/ServletContext;Lcom/github/netty/protocol/servlet/ServletRegistration;)Lcom/github/netty/protocol/servlet/ServletFilterChain;
        23: astore_3
        24: aload_0
        25: getfield      #35                 // Field filterUrlMapper:Lcom/github/netty/protocol/servlet/util/UrlMapper;
        28: aload_1
        29: aload_3
        30: invokevirtual #77                 // Method com/github/netty/protocol/servlet/ServletFilterChain.getFilterRegistrationList:()Ljava/util/List;
        33: invokevirtual #78                 // Method com/github/netty/protocol/servlet/util/UrlMapper.getMappingObjectsByUri:(Ljava/lang/String;Ljava/util/List;)Ljava/util/List;
        36: pop
        37: aload_3
        38: invokestatic  #79                 // Method com/github/netty/protocol/servlet/ServletRequestDispatcher.newInstance:(Lcom/github/netty/protocol/servlet/ServletFilterChain;)Lcom/github/netty/protocol/servlet/ServletRequestDispatcher;
        41: astore        4
        43: aload         4
        45: aload_1
        46: invokevirtual #80                 // Method com/github/netty/protocol/servlet/ServletRequestDispatcher.setPath:(Ljava/lang/String;)V
        49: aload         4
        51: areturn
      LineNumberTable:
        line 224: 0
        line 225: 12
        line 226: 16
        line 229: 18
        line 230: 24
        line 232: 37
        line 233: 43
        line 234: 49
      LocalVariableTable:
        Start  Length  Slot  Name   Signature
            0      52     0  this   Lcom/github/netty/protocol/servlet/ServletContext;
            0      52     1  path   Ljava/lang/String;
           12      40     2 servletRegistration   Lcom/github/netty/protocol/servlet/ServletRegistration;
           24      28     3 filterChain   Lcom/github/netty/protocol/servlet/ServletFilterChain;
           43       9     4 dispatcher   Lcom/github/netty/protocol/servlet/ServletRequestDispatcher;
      StackMapTable: number_of_entries = 1
        frame_type = 252 /* append */
          offset_delta = 18
          locals = [ class com/github/netty/protocol/servlet/ServletRegistration ]

  public com.github.netty.protocol.servlet.ServletRequestDispatcher getNamedDispatcher(java.lang.String);
    descriptor: (Ljava/lang/String;)Lcom/github/netty/protocol/servlet/ServletRequestDispatcher;
    flags: ACC_PUBLIC
    Code:
      stack=2, locals=9, args_size=2
         0: aconst_null
         1: aload_1
         2: if_acmpne     9
         5: aconst_null
         6: goto          14
         9: aload_0
        10: aload_1
        11: invokevirtual #81                 // Method getServletRegistration:(Ljava/lang/String;)Lcom/github/netty/protocol/servlet/ServletRegistration;
        14: astore_2
        15: aload_2
        16: ifnonnull     21
        19: aconst_null
        20: areturn
        21: aload_0
        22: aload_2
        23: invokestatic  #76                 // Method com/github/netty/protocol/servlet/ServletFilterChain.newInstance:(Lcom/github/netty/protocol/servlet/ServletContext;Lcom/github/netty/protocol/servlet/ServletRegistration;)Lcom/github/netty/protocol/servlet/ServletFilterChain;
        26: astore_3
        27: aload_3
        28: invokevirtual #77                 // Method com/github/netty/protocol/servlet/ServletFilterChain.getFilterRegistrationList:()Ljava/util/List;
        31: astore        4
        33: aload_0
        34: getfield      #12                 // Field filterRegistrationMap:Ljava/util/Map;
        37: invokeinterface #82,  1           // InterfaceMethod java/util/Map.values:()Ljava/util/Collection;
        42: invokeinterface #83,  1           // InterfaceMethod java/util/Collection.iterator:()Ljava/util/Iterator;
        47: astore        5
        49: aload         5
        51: invokeinterface #84,  1           // InterfaceMethod java/util/Iterator.hasNext:()Z
        56: ifeq          130
        59: aload         5
        61: invokeinterface #85,  1           // InterfaceMethod java/util/Iterator.next:()Ljava/lang/Object;
        66: checkcast     #86                 // class com/github/netty/protocol/servlet/ServletFilterRegistration
        69: astore        6
        71: aload         6
        73: invokevirtual #87                 // Method com/github/netty/protocol/servlet/ServletFilterRegistration.getServletNameMappings:()Ljava/util/Collection;
        76: invokeinterface #83,  1           // InterfaceMethod java/util/Collection.iterator:()Ljava/util/Iterator;
        81: astore        7
        83: aload         7
        85: invokeinterface #84,  1           // InterfaceMethod java/util/Iterator.hasNext:()Z
        90: ifeq          127
        93: aload         7
        95: invokeinterface #85,  1           // InterfaceMethod java/util/Iterator.next:()Ljava/lang/Object;
       100: checkcast     #88                 // class java/lang/String
       103: astore        8
       105: aload         8
       107: aload_1
       108: invokevirtual #89                 // Method java/lang/String.equals:(Ljava/lang/Object;)Z
       111: ifeq          124
       114: aload         4
       116: aload         6
       118: invokeinterface #90,  2           // InterfaceMethod java/util/List.add:(Ljava/lang/Object;)Z
       123: pop
       124: goto          83
       127: goto          49
       130: aload_3
       131: invokestatic  #79                 // Method com/github/netty/protocol/servlet/ServletRequestDispatcher.newInstance:(Lcom/github/netty/protocol/servlet/ServletFilterChain;)Lcom/github/netty/protocol/servlet/ServletRequestDispatcher;
       134: astore        5
       136: aload         5
       138: aload_1
       139: invokevirtual #91                 // Method com/github/netty/protocol/servlet/ServletRequestDispatcher.setName:(Ljava/lang/String;)V
       142: aload         5
       144: areturn
      LineNumberTable:
        line 239: 0
        line 240: 15
        line 241: 19
        line 244: 21
        line 245: 27
        line 246: 33
        line 247: 71
        line 248: 105
        line 249: 114
        line 251: 124
        line 252: 127
        line 254: 130
        line 255: 136
        line 256: 142
      LocalVariableTable:
        Start  Length  Slot  Name   Signature
          105      19     8 servletName   Ljava/lang/String;
           71      56     6 registration   Lcom/github/netty/protocol/servlet/ServletFilterRegistration;
            0     145     0  this   Lcom/github/netty/protocol/servlet/ServletContext;
            0     145     1  name   Ljava/lang/String;
           15     130     2 servletRegistration   Lcom/github/netty/protocol/servlet/ServletRegistration;
           27     118     3 filterChain   Lcom/github/netty/protocol/servlet/ServletFilterChain;
           33     112     4 filterList   Ljava/util/List;
          136       9     5 dispatcher   Lcom/github/netty/protocol/servlet/ServletRequestDispatcher;
      LocalVariableTypeTable:
        Start  Length  Slot  Name   Signature
           33     112     4 filterList   Ljava/util/List<Lcom/github/netty/protocol/servlet/ServletFilterRegistration;>;
      StackMapTable: number_of_entries = 8
        frame_type = 9 /* same */
        frame_type = 68 /* same_locals_1_stack_item */
          stack = [ class com/github/netty/protocol/servlet/ServletRegistration ]
        frame_type = 252 /* append */
          offset_delta = 6
          locals = [ class com/github/netty/protocol/servlet/ServletRegistration ]
        frame_type = 254 /* append */
          offset_delta = 27
          locals = [ class com/github/netty/protocol/servlet/ServletFilterChain, class java/util/List, class java/util/Iterator ]
        frame_type = 253 /* append */
          offset_delta = 33
          locals = [ class com/github/netty/protocol/servlet/ServletFilterRegistration, class java/util/Iterator ]
        frame_type = 40 /* same */
        frame_type = 249 /* chop */
          offset_delta = 2
        frame_type = 250 /* chop */
          offset_delta = 2

  public javax.servlet.Servlet getServlet(java.lang.String) throws javax.servlet.ServletException;
    descriptor: (Ljava/lang/String;)Ljavax/servlet/Servlet;
    flags: ACC_PUBLIC
    Code:
      stack=2, locals=3, args_size=2
         0: aload_0
         1: getfield      #11                 // Field servletRegistrationMap:Ljava/util/Map;
         4: aload_1
         5: invokeinterface #92,  2           // InterfaceMethod java/util/Map.get:(Ljava/lang/Object;)Ljava/lang/Object;
        10: checkcast     #75                 // class com/github/netty/protocol/servlet/ServletRegistration
        13: astore_2
        14: aload_2
        15: ifnonnull     20
        18: aconst_null
        19: areturn
        20: aload_2
        21: invokevirtual #93                 // Method com/github/netty/protocol/servlet/ServletRegistration.getServlet:()Ljavax/servlet/Servlet;
        24: areturn
      LineNumberTable:
        line 261: 0
        line 262: 14
        line 263: 18
        line 265: 20
      LocalVariableTable:
        Start  Length  Slot  Name   Signature
            0      25     0  this   Lcom/github/netty/protocol/servlet/ServletContext;
            0      25     1  name   Ljava/lang/String;
           14      11     2 registration   Lcom/github/netty/protocol/servlet/ServletRegistration;
      StackMapTable: number_of_entries = 1
        frame_type = 252 /* append */
          offset_delta = 20
          locals = [ class com/github/netty/protocol/servlet/ServletRegistration ]
    Exceptions:
      throws javax.servlet.ServletException

  public java.util.Enumeration<javax.servlet.Servlet> getServlets();
    descriptor: ()Ljava/util/Enumeration;
    flags: ACC_PUBLIC
    Code:
      stack=2, locals=4, args_size=1
         0: new           #94                 // class java/util/ArrayList
         3: dup
         4: invokespecial #95                 // Method java/util/ArrayList."<init>":()V
         7: astore_1
         8: aload_0
         9: getfield      #11                 // Field servletRegistrationMap:Ljava/util/Map;
        12: invokeinterface #82,  1           // InterfaceMethod java/util/Map.values:()Ljava/util/Collection;
        17: invokeinterface #83,  1           // InterfaceMethod java/util/Collection.iterator:()Ljava/util/Iterator;
        22: astore_2
        23: aload_2
        24: invokeinterface #84,  1           // InterfaceMethod java/util/Iterator.hasNext:()Z
        29: ifeq          56
        32: aload_2
        33: invokeinterface #85,  1           // InterfaceMethod java/util/Iterator.next:()Ljava/lang/Object;
        38: checkcast     #75                 // class com/github/netty/protocol/servlet/ServletRegistration
        41: astore_3
        42: aload_1
        43: aload_3
        44: invokevirtual #93                 // Method com/github/netty/protocol/servlet/ServletRegistration.getServlet:()Ljavax/servlet/Servlet;
        47: invokeinterface #90,  2           // InterfaceMethod java/util/List.add:(Ljava/lang/Object;)Z
        52: pop
        53: goto          23
        56: aload_1
        57: invokestatic  #96                 // Method java/util/Collections.enumeration:(Ljava/util/Collection;)Ljava/util/Enumeration;
        60: areturn
      LineNumberTable:
        line 270: 0
        line 271: 8
        line 272: 42
        line 273: 53
        line 274: 56
      LocalVariableTable:
        Start  Length  Slot  Name   Signature
           42      11     3 registration   Lcom/github/netty/protocol/servlet/ServletRegistration;
            0      61     0  this   Lcom/github/netty/protocol/servlet/ServletContext;
            8      53     1  list   Ljava/util/List;
      LocalVariableTypeTable:
        Start  Length  Slot  Name   Signature
            8      53     1  list   Ljava/util/List<Ljavax/servlet/Servlet;>;
      StackMapTable: number_of_entries = 2
        frame_type = 253 /* append */
          offset_delta = 23
          locals = [ class java/util/List, class java/util/Iterator ]
        frame_type = 250 /* chop */
          offset_delta = 32
    Signature: #335                         // ()Ljava/util/Enumeration<Ljavax/servlet/Servlet;>;

  public java.util.Enumeration<java.lang.String> getServletNames();
    descriptor: ()Ljava/util/Enumeration;
    flags: ACC_PUBLIC
    Code:
      stack=2, locals=4, args_size=1
         0: new           #94                 // class java/util/ArrayList
         3: dup
         4: invokespecial #95                 // Method java/util/ArrayList."<init>":()V
         7: astore_1
         8: aload_0
         9: getfield      #11                 // Field servletRegistrationMap:Ljava/util/Map;
        12: invokeinterface #82,  1           // InterfaceMethod java/util/Map.values:()Ljava/util/Collection;
        17: invokeinterface #83,  1           // InterfaceMethod java/util/Collection.iterator:()Ljava/util/Iterator;
        22: astore_2
        23: aload_2
        24: invokeinterface #84,  1           // InterfaceMethod java/util/Iterator.hasNext:()Z
        29: ifeq          56
        32: aload_2
        33: invokeinterface #85,  1           // InterfaceMethod java/util/Iterator.next:()Ljava/lang/Object;
        38: checkcast     #75                 // class com/github/netty/protocol/servlet/ServletRegistration
        41: astore_3
        42: aload_1
        43: aload_3
        44: invokevirtual #97                 // Method com/github/netty/protocol/servlet/ServletRegistration.getName:()Ljava/lang/String;
        47: invokeinterface #90,  2           // InterfaceMethod java/util/List.add:(Ljava/lang/Object;)Z
        52: pop
        53: goto          23
        56: aload_1
        57: invokestatic  #96                 // Method java/util/Collections.enumeration:(Ljava/util/Collection;)Ljava/util/Enumeration;
        60: areturn
      LineNumberTable:
        line 279: 0
        line 280: 8
        line 281: 42
        line 282: 53
        line 283: 56
      LocalVariableTable:
        Start  Length  Slot  Name   Signature
           42      11     3 registration   Lcom/github/netty/protocol/servlet/ServletRegistration;
            0      61     0  this   Lcom/github/netty/protocol/servlet/ServletContext;
            8      53     1  list   Ljava/util/List;
      LocalVariableTypeTable:
        Start  Length  Slot  Name   Signature
            8      53     1  list   Ljava/util/List<Ljava/lang/String;>;
      StackMapTable: number_of_entries = 2
        frame_type = 253 /* append */
          offset_delta = 23
          locals = [ class java/util/List, class java/util/Iterator ]
        frame_type = 250 /* chop */
          offset_delta = 32
    Signature: #338                         // ()Ljava/util/Enumeration<Ljava/lang/String;>;

  public void log(java.lang.String);
    descriptor: (Ljava/lang/String;)V
    flags: ACC_PUBLIC
    Code:
      stack=2, locals=2, args_size=2
         0: aload_0
         1: getfield      #4                  // Field logger:Lcom/github/netty/core/util/LoggerX;
         4: aload_1
         5: invokevirtual #98                 // Method com/github/netty/core/util/LoggerX.debug:(Ljava/lang/String;)V
         8: return
      LineNumberTable:
        line 288: 0
        line 289: 8
      LocalVariableTable:
        Start  Length  Slot  Name   Signature
            0       9     0  this   Lcom/github/netty/protocol/servlet/ServletContext;
            0       9     1   msg   Ljava/lang/String;

  public void log(java.lang.Exception, java.lang.String);
    descriptor: (Ljava/lang/Exception;Ljava/lang/String;)V
    flags: ACC_PUBLIC
    Code:
      stack=3, locals=3, args_size=3
         0: aload_0
         1: getfield      #4                  // Field logger:Lcom/github/netty/core/util/LoggerX;
         4: aload_2
         5: aload_1
         6: invokevirtual #99                 // Method com/github/netty/core/util/LoggerX.debug:(Ljava/lang/String;Ljava/lang/Throwable;)V
         9: return
      LineNumberTable:
        line 293: 0
        line 294: 9
      LocalVariableTable:
        Start  Length  Slot  Name   Signature
            0      10     0  this   Lcom/github/netty/protocol/servlet/ServletContext;
            0      10     1 exception   Ljava/lang/Exception;
            0      10     2   msg   Ljava/lang/String;

  public void log(java.lang.String, java.lang.Throwable);
    descriptor: (Ljava/lang/String;Ljava/lang/Throwable;)V
    flags: ACC_PUBLIC
    Code:
      stack=3, locals=3, args_size=3
         0: aload_0
         1: getfield      #4                  // Field logger:Lcom/github/netty/core/util/LoggerX;
         4: aload_1
         5: aload_2
         6: invokevirtual #99                 // Method com/github/netty/core/util/LoggerX.debug:(Ljava/lang/String;Ljava/lang/Throwable;)V
         9: return
      LineNumberTable:
        line 298: 0
        line 299: 9
      LocalVariableTable:
        Start  Length  Slot  Name   Signature
            0      10     0  this   Lcom/github/netty/protocol/servlet/ServletContext;
            0      10     1 message   Ljava/lang/String;
            0      10     2 throwable   Ljava/lang/Throwable;

  public java.lang.String getServerInfo();
    descriptor: ()Ljava/lang/String;
    flags: ACC_PUBLIC
    Code:
      stack=2, locals=1, args_size=1
         0: invokestatic  #100                // Method com/github/netty/protocol/servlet/util/ServletUtil.getServerInfo:()Ljava/lang/String;
         3: ldc           #101                // String (JDK
         5: invokevirtual #102                // Method java/lang/String.concat:(Ljava/lang/String;)Ljava/lang/String;
         8: invokestatic  #103                // Method com/github/netty/protocol/servlet/util/ServletUtil.getJvmVersion:()Ljava/lang/String;
        11: invokevirtual #102                // Method java/lang/String.concat:(Ljava/lang/String;)Ljava/lang/String;
        14: ldc           #104                // String ;
        16: invokevirtual #102                // Method java/lang/String.concat:(Ljava/lang/String;)Ljava/lang/String;
        19: invokestatic  #105                // Method com/github/netty/protocol/servlet/util/ServletUtil.getOsName:()Ljava/lang/String;
        22: invokevirtual #102                // Method java/lang/String.concat:(Ljava/lang/String;)Ljava/lang/String;
        25: ldc           #106                // String
        27: invokevirtual #102                // Method java/lang/String.concat:(Ljava/lang/String;)Ljava/lang/String;
        30: invokestatic  #107                // Method com/github/netty/protocol/servlet/util/ServletUtil.getArch:()Ljava/lang/String;
        33: invokevirtual #102                // Method java/lang/String.concat:(Ljava/lang/String;)Ljava/lang/String;
        36: ldc           #108                // String )
        38: invokevirtual #102                // Method java/lang/String.concat:(Ljava/lang/String;)Ljava/lang/String;
        41: areturn
      LineNumberTable:
        line 303: 0
        line 304: 5
        line 305: 8
        line 306: 16
        line 307: 19
        line 308: 27
        line 309: 30
        line 310: 38
      LocalVariableTable:
        Start  Length  Slot  Name   Signature
            0      42     0  this   Lcom/github/netty/protocol/servlet/ServletContext;

  public java.lang.String getInitParameter(java.lang.String);
    descriptor: (Ljava/lang/String;)Ljava/lang/String;
    flags: ACC_PUBLIC
    Code:
      stack=2, locals=2, args_size=2
         0: aload_0
         1: getfield      #10                 // Field initParamMap:Ljava/util/Map;
         4: aload_1
         5: invokeinterface #92,  2           // InterfaceMethod java/util/Map.get:(Ljava/lang/Object;)Ljava/lang/Object;
        10: checkcast     #88                 // class java/lang/String
        13: areturn
      LineNumberTable:
        line 315: 0
      LocalVariableTable:
        Start  Length  Slot  Name   Signature
            0      14     0  this   Lcom/github/netty/protocol/servlet/ServletContext;
            0      14     1  name   Ljava/lang/String;

  public <T extends java.lang.Object> T getInitParameter(java.lang.String, T);
    descriptor: (Ljava/lang/String;Ljava/lang/Object;)Ljava/lang/Object;
    flags: ACC_PUBLIC
    Code:
      stack=2, locals=6, args_size=3
         0: aload_0
         1: aload_1
         2: invokevirtual #60                 // Method getInitParameter:(Ljava/lang/String;)Ljava/lang/String;
         5: astore_3
         6: aload_3
         7: ifnonnull     12
        10: aload_2
        11: areturn
        12: aload_2
        13: invokevirtual #2                  // Method java/lang/Object.getClass:()Ljava/lang/Class;
        16: astore        4
        18: aload_3
        19: aload         4
        21: invokestatic  #109                // Method com/github/netty/core/util/TypeUtil.cast:(Ljava/lang/Object;Ljava/lang/Class;)Ljava/lang/Object;
        24: astore        5
        26: aload         5
        28: ifnull        47
        31: aload         5
        33: invokevirtual #2                  // Method java/lang/Object.getClass:()Ljava/lang/Class;
        36: aload         4
        38: invokevirtual #110                // Method java/lang/Class.isAssignableFrom:(Ljava/lang/Class;)Z
        41: ifeq          47
        44: aload         5
        46: areturn
        47: aload_2
        48: areturn
      LineNumberTable:
        line 319: 0
        line 320: 6
        line 321: 10
        line 323: 12
        line 324: 18
        line 325: 26
        line 326: 44
        line 328: 47
      LocalVariableTable:
        Start  Length  Slot  Name   Signature
            0      49     0  this   Lcom/github/netty/protocol/servlet/ServletContext;
            0      49     1  name   Ljava/lang/String;
            0      49     2   def   Ljava/lang/Object;
            6      43     3 value   Ljava/lang/String;
           18      31     4 clazz   Ljava/lang/Class;
           26      23     5 valCast   Ljava/lang/Object;
      LocalVariableTypeTable:
        Start  Length  Slot  Name   Signature
            0      49     2   def   TT;
           18      31     4 clazz   Ljava/lang/Class<*>;
      StackMapTable: number_of_entries = 2
        frame_type = 252 /* append */
          offset_delta = 12
          locals = [ class java/lang/String ]
        frame_type = 253 /* append */
          offset_delta = 34
          locals = [ class java/lang/Class, class java/lang/Object ]
    Signature: #359                         // <T:Ljava/lang/Object;>(Ljava/lang/String;TT;)TT;

  public java.util.Enumeration<java.lang.String> getInitParameterNames();
    descriptor: ()Ljava/util/Enumeration;
    flags: ACC_PUBLIC
    Code:
      stack=1, locals=1, args_size=1
         0: aload_0
         1: getfield      #10                 // Field initParamMap:Ljava/util/Map;
         4: invokeinterface #111,  1          // InterfaceMethod java/util/Map.keySet:()Ljava/util/Set;
         9: invokestatic  #96                 // Method java/util/Collections.enumeration:(Ljava/util/Collection;)Ljava/util/Enumeration;
        12: areturn
      LineNumberTable:
        line 333: 0
      LocalVariableTable:
        Start  Length  Slot  Name   Signature
            0      13     0  this   Lcom/github/netty/protocol/servlet/ServletContext;
    Signature: #338                         // ()Ljava/util/Enumeration<Ljava/lang/String;>;

  public boolean setInitParameter(java.lang.String, java.lang.String);
    descriptor: (Ljava/lang/String;Ljava/lang/String;)Z
    flags: ACC_PUBLIC
    Code:
      stack=3, locals=3, args_size=3
         0: aload_0
         1: getfield      #10                 // Field initParamMap:Ljava/util/Map;
         4: aload_1
         5: aload_2
         6: invokeinterface #112,  3          // InterfaceMethod java/util/Map.putIfAbsent:(Ljava/lang/Object;Ljava/lang/Object;)Ljava/lang/Object;
        11: ifnonnull     18
        14: iconst_1
        15: goto          19
        18: iconst_0
        19: ireturn
      LineNumberTable:
        line 338: 0
      LocalVariableTable:
        Start  Length  Slot  Name   Signature
            0      20     0  this   Lcom/github/netty/protocol/servlet/ServletContext;
            0      20     1  name   Ljava/lang/String;
            0      20     2 value   Ljava/lang/String;
      StackMapTable: number_of_entries = 2
        frame_type = 18 /* same */
        frame_type = 64 /* same_locals_1_stack_item */
          stack = [ int ]

  public java.lang.Object getAttribute(java.lang.String);
    descriptor: (Ljava/lang/String;)Ljava/lang/Object;
    flags: ACC_PUBLIC
    Code:
      stack=2, locals=2, args_size=2
         0: aload_0
         1: getfield      #9                  // Field attributeMap:Ljava/util/Map;
         4: aload_1
         5: invokeinterface #92,  2           // InterfaceMethod java/util/Map.get:(Ljava/lang/Object;)Ljava/lang/Object;
        10: areturn
      LineNumberTable:
        line 343: 0
      LocalVariableTable:
        Start  Length  Slot  Name   Signature
            0      11     0  this   Lcom/github/netty/protocol/servlet/ServletContext;
            0      11     1  name   Ljava/lang/String;

  public java.util.Enumeration<java.lang.String> getAttributeNames();
    descriptor: ()Ljava/util/Enumeration;
    flags: ACC_PUBLIC
    Code:
      stack=1, locals=1, args_size=1
         0: aload_0
         1: getfield      #9                  // Field attributeMap:Ljava/util/Map;
         4: invokeinterface #111,  1          // InterfaceMethod java/util/Map.keySet:()Ljava/util/Set;
         9: invokestatic  #96                 // Method java/util/Collections.enumeration:(Ljava/util/Collection;)Ljava/util/Enumeration;
        12: areturn
      LineNumberTable:
        line 348: 0
      LocalVariableTable:
        Start  Length  Slot  Name   Signature
            0      13     0  this   Lcom/github/netty/protocol/servlet/ServletContext;
    Signature: #338                         // ()Ljava/util/Enumeration<Ljava/lang/String;>;

  public void setAttribute(java.lang.String, java.lang.Object);
    descriptor: (Ljava/lang/String;Ljava/lang/Object;)V
    flags: ACC_PUBLIC
    Code:
      stack=6, locals=5, args_size=3
         0: aload_1
         1: invokestatic  #36                 // Method java/util/Objects.requireNonNull:(Ljava/lang/Object;)Ljava/lang/Object;
         4: pop
         5: aload_2
         6: ifnonnull     15
         9: aload_0
        10: aload_1
        11: invokevirtual #113                // Method removeAttribute:(Ljava/lang/String;)V
        14: return
        15: aload_0
        16: getfield      #9                  // Field attributeMap:Ljava/util/Map;
        19: aload_1
        20: aload_2
        21: invokeinterface #114,  3          // InterfaceMethod java/util/Map.put:(Ljava/lang/Object;Ljava/lang/Object;)Ljava/lang/Object;
        26: astore_3
        27: aload_0
        28: invokevirtual #115                // Method getServletEventListenerManager:()Lcom/github/netty/protocol/servlet/ServletEventListenerManager;
        31: astore        4
        33: aload         4
        35: invokevirtual #116                // Method com/github/netty/protocol/servlet/ServletEventListenerManager.hasServletContextAttributeListener:()Z
        38: ifeq          75
        41: aload         4
        43: new           #117                // class javax/servlet/ServletContextAttributeEvent
        46: dup
        47: aload_0
        48: aload_1
        49: aload_2
        50: invokespecial #118                // Method javax/servlet/ServletContextAttributeEvent."<init>":(Ljavax/servlet/ServletContext;Ljava/lang/String;Ljava/lang/Object;)V
        53: invokevirtual #119                // Method com/github/netty/protocol/servlet/ServletEventListenerManager.onServletContextAttributeAdded:(Ljavax/servlet/ServletContextAttributeEvent;)V
        56: aload_3
        57: ifnull        75
        60: aload         4
        62: new           #117                // class javax/servlet/ServletContextAttributeEvent
        65: dup
        66: aload_0
        67: aload_1
        68: aload_3
        69: invokespecial #118                // Method javax/servlet/ServletContextAttributeEvent."<init>":(Ljavax/servlet/ServletContext;Ljava/lang/String;Ljava/lang/Object;)V
        72: invokevirtual #120                // Method com/github/netty/protocol/servlet/ServletEventListenerManager.onServletContextAttributeReplaced:(Ljavax/servlet/ServletContextAttributeEvent;)V
        75: return
      LineNumberTable:
        line 353: 0
        line 354: 5
        line 355: 9
        line 356: 14
        line 359: 15
        line 360: 27
        line 361: 33
        line 362: 41
        line 363: 56
        line 364: 60
        line 367: 75
      LocalVariableTable:
        Start  Length  Slot  Name   Signature
            0      76     0  this   Lcom/github/netty/protocol/servlet/ServletContext;
            0      76     1  name   Ljava/lang/String;
            0      76     2 object   Ljava/lang/Object;
           27      49     3 oldObject   Ljava/lang/Object;
           33      43     4 listenerManager   Lcom/github/netty/protocol/servlet/ServletEventListenerManager;
      StackMapTable: number_of_entries = 2
        frame_type = 15 /* same */
        frame_type = 253 /* append */
          offset_delta = 59
          locals = [ class java/lang/Object, class com/github/netty/protocol/servlet/ServletEventListenerManager ]

  public void removeAttribute(java.lang.String);
    descriptor: (Ljava/lang/String;)V
    flags: ACC_PUBLIC
    Code:
      stack=6, locals=4, args_size=2
         0: aload_0
         1: getfield      #9                  // Field attributeMap:Ljava/util/Map;
         4: aload_1
         5: invokeinterface #121,  2          // InterfaceMethod java/util/Map.remove:(Ljava/lang/Object;)Ljava/lang/Object;
        10: astore_2
        11: aload_0
        12: invokevirtual #115                // Method getServletEventListenerManager:()Lcom/github/netty/protocol/servlet/ServletEventListenerManager;
        15: astore_3
        16: aload_3
        17: invokevirtual #116                // Method com/github/netty/protocol/servlet/ServletEventListenerManager.hasServletContextAttributeListener:()Z
        20: ifeq          37
        23: aload_3
        24: new           #117                // class javax/servlet/ServletContextAttributeEvent
        27: dup
        28: aload_0
        29: aload_1
        30: aload_2
        31: invokespecial #118                // Method javax/servlet/ServletContextAttributeEvent."<init>":(Ljavax/servlet/ServletContext;Ljava/lang/String;Ljava/lang/Object;)V
        34: invokevirtual #122                // Method com/github/netty/protocol/servlet/ServletEventListenerManager.onServletContextAttributeRemoved:(Ljavax/servlet/ServletContextAttributeEvent;)V
        37: return
      LineNumberTable:
        line 371: 0
        line 372: 11
        line 373: 16
        line 374: 23
        line 376: 37
      LocalVariableTable:
        Start  Length  Slot  Name   Signature
            0      38     0  this   Lcom/github/netty/protocol/servlet/ServletContext;
            0      38     1  name   Ljava/lang/String;
           11      27     2 oldObject   Ljava/lang/Object;
           16      22     3 listenerManager   Lcom/github/netty/protocol/servlet/ServletEventListenerManager;
      StackMapTable: number_of_entries = 1
        frame_type = 253 /* append */
          offset_delta = 37
          locals = [ class java/lang/Object, class com/github/netty/protocol/servlet/ServletEventListenerManager ]

  public java.lang.String getServletContextName();
    descriptor: ()Ljava/lang/String;
    flags: ACC_PUBLIC
    Code:
      stack=1, locals=1, args_size=1
         0: aload_0
         1: getfield      #56                 // Field servletContextName:Ljava/lang/String;
         4: areturn
      LineNumberTable:
        line 380: 0
      LocalVariableTable:
        Start  Length  Slot  Name   Signature
            0       5     0  this   Lcom/github/netty/protocol/servlet/ServletContext;

  public com.github.netty.protocol.servlet.ServletRegistration addServlet(java.lang.String, java.lang.String);
    descriptor: (Ljava/lang/String;Ljava/lang/String;)Lcom/github/netty/protocol/servlet/ServletRegistration;
    flags: ACC_PUBLIC
    Code:
      stack=3, locals=4, args_size=3
         0: aload_0
         1: aload_1
         2: aload_2
         3: invokestatic  #123                // Method java/lang/Class.forName:(Ljava/lang/String;)Ljava/lang/Class;
         6: invokevirtual #124                // Method java/lang/Class.newInstance:()Ljava/lang/Object;
         9: checkcast     #125                // class java/lang/Class
        12: invokevirtual #126                // Method addServlet:(Ljava/lang/String;Ljava/lang/Class;)Lcom/github/netty/protocol/servlet/ServletRegistration;
        15: areturn
        16: astore_3
        17: aload_3
        18: invokevirtual #130                // Method java/lang/ReflectiveOperationException.printStackTrace:()V
        21: aconst_null
        22: areturn
      Exception table:
         from    to  target type
             0    15    16   Class java/lang/InstantiationException
             0    15    16   Class java/lang/IllegalAccessException
             0    15    16   Class java/lang/ClassNotFoundException
      LineNumberTable:
        line 386: 0
        line 387: 16
        line 388: 17
        line 390: 21
      LocalVariableTable:
        Start  Length  Slot  Name   Signature
           17       4     3     e   Ljava/lang/ReflectiveOperationException;
            0      23     0  this   Lcom/github/netty/protocol/servlet/ServletContext;
            0      23     1 servletName   Ljava/lang/String;
            0      23     2 className   Ljava/lang/String;
      StackMapTable: number_of_entries = 1
        frame_type = 80 /* same_locals_1_stack_item */
          stack = [ class java/lang/ReflectiveOperationException ]

  public com.github.netty.protocol.servlet.ServletRegistration addServlet(java.lang.String, javax.servlet.Servlet);
    descriptor: (Ljava/lang/String;Ljavax/servlet/Servlet;)Lcom/github/netty/protocol/servlet/ServletRegistration;
    flags: ACC_PUBLIC
    Code:
      stack=6, locals=5, args_size=3
         0: aload_0
         1: getfield      #28                 // Field servletEventListenerManager:Lcom/github/netty/protocol/servlet/ServletEventListenerManager;
         4: aload_2
         5: invokevirtual #131                // Method com/github/netty/protocol/servlet/ServletEventListenerManager.onServletAdded:(Ljavax/servlet/Servlet;)Ljavax/servlet/Servlet;
         8: astore_3
         9: aload_3
        10: ifnonnull     32
        13: new           #75                 // class com/github/netty/protocol/servlet/ServletRegistration
        16: dup
        17: aload_1
        18: aload_2
        19: aload_0
        20: aload_0
        21: getfield      #34                 // Field servletUrlMapper:Lcom/github/netty/protocol/servlet/util/UrlMapper;
        24: invokespecial #132                // Method com/github/netty/protocol/servlet/ServletRegistration."<init>":(Ljava/lang/String;Ljavax/servlet/Servlet;Lcom/github/netty/protocol/servlet/ServletContext;Lcom/github/netty/protocol/servlet/util/UrlMapper;)V
        27: astore        4
        29: goto          48
        32: new           #75                 // class com/github/netty/protocol/servlet/ServletRegistration
        35: dup
        36: aload_1
        37: aload_3
        38: aload_0
        39: aload_0
        40: getfield      #34                 // Field servletUrlMapper:Lcom/github/netty/protocol/servlet/util/UrlMapper;
        43: invokespecial #132                // Method com/github/netty/protocol/servlet/ServletRegistration."<init>":(Ljava/lang/String;Ljavax/servlet/Servlet;Lcom/github/netty/protocol/servlet/ServletContext;Lcom/github/netty/protocol/servlet/util/UrlMapper;)V
        46: astore        4
        48: aload_0
        49: getfield      #11                 // Field servletRegistrationMap:Ljava/util/Map;
        52: aload_1
        53: aload         4
        55: invokeinterface #114,  3          // InterfaceMethod java/util/Map.put:(Ljava/lang/Object;Ljava/lang/Object;)Ljava/lang/Object;
        60: pop
        61: aload         4
        63: areturn
      LineNumberTable:
        line 395: 0
        line 398: 9
        line 399: 13
        line 401: 32
        line 403: 48
        line 404: 61
      LocalVariableTable:
        Start  Length  Slot  Name   Signature
           29       3     4 servletRegistration   Lcom/github/netty/protocol/servlet/ServletRegistration;
            0      64     0  this   Lcom/github/netty/protocol/servlet/ServletContext;
            0      64     1 servletName   Ljava/lang/String;
            0      64     2 servlet   Ljavax/servlet/Servlet;
            9      55     3 newServlet   Ljavax/servlet/Servlet;
           48      16     4 servletRegistration   Lcom/github/netty/protocol/servlet/ServletRegistration;
      StackMapTable: number_of_entries = 2
        frame_type = 252 /* append */
          offset_delta = 32
          locals = [ class javax/servlet/Servlet ]
        frame_type = 252 /* append */
          offset_delta = 15
          locals = [ class com/github/netty/protocol/servlet/ServletRegistration ]

  public com.github.netty.protocol.servlet.ServletRegistration addServlet(java.lang.String, java.lang.Class<? extends javax.servlet.Servlet>);
    descriptor: (Ljava/lang/String;Ljava/lang/Class;)Lcom/github/netty/protocol/servlet/ServletRegistration;
    flags: ACC_PUBLIC
    Code:
      stack=3, locals=5, args_size=3
         0: aconst_null
         1: astore_3
         2: aload_2
         3: invokevirtual #124                // Method java/lang/Class.newInstance:()Ljava/lang/Object;
         6: checkcast     #133                // class javax/servlet/Servlet
         9: astore_3
        10: goto          20
        13: astore        4
        15: aload         4
        17: invokevirtual #130                // Method java/lang/ReflectiveOperationException.printStackTrace:()V
        20: aload_0
        21: aload_1
        22: aload_3
        23: invokevirtual #134                // Method addServlet:(Ljava/lang/String;Ljavax/servlet/Servlet;)Lcom/github/netty/protocol/servlet/ServletRegistration;
        26: areturn
      Exception table:
         from    to  target type
             2    10    13   Class java/lang/InstantiationException
             2    10    13   Class java/lang/IllegalAccessException
      LineNumberTable:
        line 409: 0
        line 411: 2
        line 414: 10
        line 412: 13
        line 413: 15
        line 415: 20
      LocalVariableTable:
        Start  Length  Slot  Name   Signature
           15       5     4     e   Ljava/lang/ReflectiveOperationException;
            0      27     0  this   Lcom/github/netty/protocol/servlet/ServletContext;
            0      27     1 servletName   Ljava/lang/String;
            0      27     2 servletClass   Ljava/lang/Class;
            2      25     3 servlet   Ljavax/servlet/Servlet;
      LocalVariableTypeTable:
        Start  Length  Slot  Name   Signature
            0      27     2 servletClass   Ljava/lang/Class<+Ljavax/servlet/Servlet;>;
      StackMapTable: number_of_entries = 2
        frame_type = 255 /* full_frame */
          offset_delta = 13
          locals = [ class com/github/netty/protocol/servlet/ServletContext, class java/lang/String, class java/lang/Class, class javax/servlet/Servlet ]
          stack = [ class java/lang/ReflectiveOperationException ]
        frame_type = 6 /* same */
    Signature: #387                         // (Ljava/lang/String;Ljava/lang/Class<+Ljavax/servlet/Servlet;>;)Lcom/github/netty/protocol/servlet/ServletRegistration;

  public <T extends javax.servlet.Servlet> T createServlet(java.lang.Class<T>) throws javax.servlet.ServletException;
    descriptor: (Ljava/lang/Class;)Ljavax/servlet/Servlet;
    flags: ACC_PUBLIC
    Code:
      stack=1, locals=3, args_size=2
         0: aload_1
         1: invokevirtual #124                // Method java/lang/Class.newInstance:()Ljava/lang/Object;
         4: checkcast     #133                // class javax/servlet/Servlet
         7: areturn
         8: astore_2
         9: aload_2
        10: invokevirtual #130                // Method java/lang/ReflectiveOperationException.printStackTrace:()V
        13: aconst_null
        14: areturn
      Exception table:
         from    to  target type
             0     7     8   Class java/lang/InstantiationException
             0     7     8   Class java/lang/IllegalAccessException
      LineNumberTable:
        line 421: 0
        line 422: 8
        line 423: 9
        line 425: 13
      LocalVariableTable:
        Start  Length  Slot  Name   Signature
            9       4     2     e   Ljava/lang/ReflectiveOperationException;
            0      15     0  this   Lcom/github/netty/protocol/servlet/ServletContext;
            0      15     1 clazz   Ljava/lang/Class;
      LocalVariableTypeTable:
        Start  Length  Slot  Name   Signature
            0      15     1 clazz   Ljava/lang/Class<TT;>;
      StackMapTable: number_of_entries = 1
        frame_type = 72 /* same_locals_1_stack_item */
          stack = [ class java/lang/ReflectiveOperationException ]
    Exceptions:
      throws javax.servlet.ServletException
    Signature: #391                         // <T::Ljavax/servlet/Servlet;>(Ljava/lang/Class<TT;>;)TT;

  public com.github.netty.protocol.servlet.ServletRegistration getServletRegistration(java.lang.String);
    descriptor: (Ljava/lang/String;)Lcom/github/netty/protocol/servlet/ServletRegistration;
    flags: ACC_PUBLIC
    Code:
      stack=2, locals=2, args_size=2
         0: aload_0
         1: getfield      #11                 // Field servletRegistrationMap:Ljava/util/Map;
         4: aload_1
         5: invokeinterface #92,  2           // InterfaceMethod java/util/Map.get:(Ljava/lang/Object;)Ljava/lang/Object;
        10: checkcast     #75                 // class com/github/netty/protocol/servlet/ServletRegistration
        13: areturn
      LineNumberTable:
        line 430: 0
      LocalVariableTable:
        Start  Length  Slot  Name   Signature
            0      14     0  this   Lcom/github/netty/protocol/servlet/ServletContext;
            0      14     1 servletName   Ljava/lang/String;

  public java.util.Map<java.lang.String, com.github.netty.protocol.servlet.ServletRegistration> getServletRegistrations();
    descriptor: ()Ljava/util/Map;
    flags: ACC_PUBLIC
    Code:
      stack=1, locals=1, args_size=1
         0: aload_0
         1: getfield      #11                 // Field servletRegistrationMap:Ljava/util/Map;
         4: areturn
      LineNumberTable:
        line 435: 0
      LocalVariableTable:
        Start  Length  Slot  Name   Signature
            0       5     0  this   Lcom/github/netty/protocol/servlet/ServletContext;
    Signature: #396                         // ()Ljava/util/Map<Ljava/lang/String;Lcom/github/netty/protocol/servlet/ServletRegistration;>;

  public com.github.netty.protocol.servlet.ServletFilterRegistration addFilter(java.lang.String, java.lang.String);
    descriptor: (Ljava/lang/String;Ljava/lang/String;)Lcom/github/netty/protocol/servlet/ServletFilterRegistration;
    flags: ACC_PUBLIC
    Code:
      stack=3, locals=4, args_size=3
         0: aload_0
         1: aload_1
         2: aload_2
         3: invokestatic  #123                // Method java/lang/Class.forName:(Ljava/lang/String;)Ljava/lang/Class;
         6: invokevirtual #135                // Method addFilter:(Ljava/lang/String;Ljava/lang/Class;)Lcom/github/netty/protocol/servlet/ServletFilterRegistration;
         9: areturn
        10: astore_3
        11: aload_3
        12: invokevirtual #136                // Method java/lang/ClassNotFoundException.printStackTrace:()V
        15: aconst_null
        16: areturn
      Exception table:
         from    to  target type
             0     9    10   Class java/lang/ClassNotFoundException
      LineNumberTable:
        line 441: 0
        line 442: 10
        line 443: 11
        line 445: 15
      LocalVariableTable:
        Start  Length  Slot  Name   Signature
           11       4     3     e   Ljava/lang/ClassNotFoundException;
            0      17     0  this   Lcom/github/netty/protocol/servlet/ServletContext;
            0      17     1 filterName   Ljava/lang/String;
            0      17     2 className   Ljava/lang/String;
      StackMapTable: number_of_entries = 1
        frame_type = 74 /* same_locals_1_stack_item */
          stack = [ class java/lang/ClassNotFoundException ]

  public com.github.netty.protocol.servlet.ServletFilterRegistration addFilter(java.lang.String, javax.servlet.Filter);
    descriptor: (Ljava/lang/String;Ljavax/servlet/Filter;)Lcom/github/netty/protocol/servlet/ServletFilterRegistration;
    flags: ACC_PUBLIC
    Code:
      stack=6, locals=4, args_size=3
         0: new           #86                 // class com/github/netty/protocol/servlet/ServletFilterRegistration
         3: dup
         4: aload_1
         5: aload_2
         6: aload_0
         7: aload_0
         8: getfield      #35                 // Field filterUrlMapper:Lcom/github/netty/protocol/servlet/util/UrlMapper;
        11: invokespecial #137                // Method com/github/netty/protocol/servlet/ServletFilterRegistration."<init>":(Ljava/lang/String;Ljavax/servlet/Filter;Lcom/github/netty/protocol/servlet/ServletContext;Lcom/github/netty/protocol/servlet/util/UrlMapper;)V
        14: astore_3
        15: aload_0
        16: getfield      #12                 // Field filterRegistrationMap:Ljava/util/Map;
        19: aload_1
        20: aload_3
        21: invokeinterface #114,  3          // InterfaceMethod java/util/Map.put:(Ljava/lang/Object;Ljava/lang/Object;)Ljava/lang/Object;
        26: pop
        27: aload_3
        28: areturn
      LineNumberTable:
        line 450: 0
        line 451: 15
        line 452: 27
      LocalVariableTable:
        Start  Length  Slot  Name   Signature
            0      29     0  this   Lcom/github/netty/protocol/servlet/ServletContext;
            0      29     1 filterName   Ljava/lang/String;
            0      29     2 filter   Ljavax/servlet/Filter;
           15      14     3 registration   Lcom/github/netty/protocol/servlet/ServletFilterRegistration;

  public com.github.netty.protocol.servlet.ServletFilterRegistration addFilter(java.lang.String, java.lang.Class<? extends javax.servlet.Filter>);
    descriptor: (Ljava/lang/String;Ljava/lang/Class;)Lcom/github/netty/protocol/servlet/ServletFilterRegistration;
    flags: ACC_PUBLIC
    Code:
      stack=3, locals=4, args_size=3
         0: aload_0
         1: aload_1
         2: aload_2
         3: invokevirtual #124                // Method java/lang/Class.newInstance:()Ljava/lang/Object;
         6: checkcast     #138                // class javax/servlet/Filter
         9: invokevirtual #139                // Method addFilter:(Ljava/lang/String;Ljavax/servlet/Filter;)Lcom/github/netty/protocol/servlet/ServletFilterRegistration;
        12: areturn
        13: astore_3
        14: aload_3
        15: invokevirtual #130                // Method java/lang/ReflectiveOperationException.printStackTrace:()V
        18: aconst_null
        19: areturn
      Exception table:
         from    to  target type
             0    12    13   Class java/lang/InstantiationException
             0    12    13   Class java/lang/IllegalAccessException
      LineNumberTable:
        line 458: 0
        line 459: 13
        line 460: 14
        line 462: 18
      LocalVariableTable:
        Start  Length  Slot  Name   Signature
           14       4     3     e   Ljava/lang/ReflectiveOperationException;
            0      20     0  this   Lcom/github/netty/protocol/servlet/ServletContext;
            0      20     1 filterName   Ljava/lang/String;
            0      20     2 filterClass   Ljava/lang/Class;
      LocalVariableTypeTable:
        Start  Length  Slot  Name   Signature
            0      20     2 filterClass   Ljava/lang/Class<+Ljavax/servlet/Filter;>;
      StackMapTable: number_of_entries = 1
        frame_type = 77 /* same_locals_1_stack_item */
          stack = [ class java/lang/ReflectiveOperationException ]
    Signature: #408                         // (Ljava/lang/String;Ljava/lang/Class<+Ljavax/servlet/Filter;>;)Lcom/github/netty/protocol/servlet/ServletFilterRegistration;

  public <T extends javax.servlet.Filter> T createFilter(java.lang.Class<T>) throws javax.servlet.ServletException;
    descriptor: (Ljava/lang/Class;)Ljavax/servlet/Filter;
    flags: ACC_PUBLIC
    Code:
      stack=1, locals=3, args_size=2
         0: aload_1
         1: invokevirtual #124                // Method java/lang/Class.newInstance:()Ljava/lang/Object;
         4: checkcast     #138                // class javax/servlet/Filter
         7: areturn
         8: astore_2
         9: aload_2
        10: invokevirtual #130                // Method java/lang/ReflectiveOperationException.printStackTrace:()V
        13: aconst_null
        14: areturn
      Exception table:
         from    to  target type
             0     7     8   Class java/lang/InstantiationException
             0     7     8   Class java/lang/IllegalAccessException
      LineNumberTable:
        line 468: 0
        line 469: 8
        line 470: 9
        line 472: 13
      LocalVariableTable:
        Start  Length  Slot  Name   Signature
            9       4     2     e   Ljava/lang/ReflectiveOperationException;
            0      15     0  this   Lcom/github/netty/protocol/servlet/ServletContext;
            0      15     1 clazz   Ljava/lang/Class;
      LocalVariableTypeTable:
        Start  Length  Slot  Name   Signature
            0      15     1 clazz   Ljava/lang/Class<TT;>;
      StackMapTable: number_of_entries = 1
        frame_type = 72 /* same_locals_1_stack_item */
          stack = [ class java/lang/ReflectiveOperationException ]
    Exceptions:
      throws javax.servlet.ServletException
    Signature: #411                         // <T::Ljavax/servlet/Filter;>(Ljava/lang/Class<TT;>;)TT;

  public javax.servlet.FilterRegistration getFilterRegistration(java.lang.String);
    descriptor: (Ljava/lang/String;)Ljavax/servlet/FilterRegistration;
    flags: ACC_PUBLIC
    Code:
      stack=2, locals=2, args_size=2
         0: aload_0
         1: getfield      #12                 // Field filterRegistrationMap:Ljava/util/Map;
         4: aload_1
         5: invokeinterface #92,  2           // InterfaceMethod java/util/Map.get:(Ljava/lang/Object;)Ljava/lang/Object;
        10: checkcast     #140                // class javax/servlet/FilterRegistration
        13: areturn
      LineNumberTable:
        line 477: 0
      LocalVariableTable:
        Start  Length  Slot  Name   Signature
            0      14     0  this   Lcom/github/netty/protocol/servlet/ServletContext;
            0      14     1 filterName   Ljava/lang/String;

  public java.util.Map<java.lang.String, com.github.netty.protocol.servlet.ServletFilterRegistration> getFilterRegistrations();
    descriptor: ()Ljava/util/Map;
    flags: ACC_PUBLIC
    Code:
      stack=1, locals=1, args_size=1
         0: aload_0
         1: getfield      #12                 // Field filterRegistrationMap:Ljava/util/Map;
         4: areturn
      LineNumberTable:
        line 482: 0
      LocalVariableTable:
        Start  Length  Slot  Name   Signature
            0       5     0  this   Lcom/github/netty/protocol/servlet/ServletContext;
    Signature: #415                         // ()Ljava/util/Map<Ljava/lang/String;Lcom/github/netty/protocol/servlet/ServletFilterRegistration;>;

  public com.github.netty.protocol.servlet.ServletSessionCookieConfig getSessionCookieConfig();
    descriptor: ()Lcom/github/netty/protocol/servlet/ServletSessionCookieConfig;
    flags: ACC_PUBLIC
    Code:
      stack=1, locals=1, args_size=1
         0: aload_0
         1: getfield      #31                 // Field sessionCookieConfig:Lcom/github/netty/protocol/servlet/ServletSessionCookieConfig;
         4: areturn
      LineNumberTable:
        line 487: 0
      LocalVariableTable:
        Start  Length  Slot  Name   Signature
            0       5     0  this   Lcom/github/netty/protocol/servlet/ServletContext;

  public void setSessionTrackingModes(java.util.Set<javax.servlet.SessionTrackingMode>);
    descriptor: (Ljava/util/Set;)V
    flags: ACC_PUBLIC
    Code:
      stack=2, locals=2, args_size=2
         0: aload_0
         1: aload_1
         2: putfield      #141                // Field sessionTrackingModeSet:Ljava/util/Set;
         5: return
      LineNumberTable:
        line 492: 0
        line 493: 5
      LocalVariableTable:
        Start  Length  Slot  Name   Signature
            0       6     0  this   Lcom/github/netty/protocol/servlet/ServletContext;
            0       6     1 sessionTrackingModes   Ljava/util/Set;
      LocalVariableTypeTable:
        Start  Length  Slot  Name   Signature
            0       6     1 sessionTrackingModes   Ljava/util/Set<Ljavax/servlet/SessionTrackingMode;>;
    Signature: #421                         // (Ljava/util/Set<Ljavax/servlet/SessionTrackingMode;>;)V

  public java.util.Set<javax.servlet.SessionTrackingMode> getDefaultSessionTrackingModes();
    descriptor: ()Ljava/util/Set;
    flags: ACC_PUBLIC
    Code:
      stack=1, locals=1, args_size=1
         0: aload_0
         1: getfield      #19                 // Field defaultSessionTrackingModeSet:Ljava/util/Set;
         4: areturn
      LineNumberTable:
        line 497: 0
      LocalVariableTable:
        Start  Length  Slot  Name   Signature
            0       5     0  this   Lcom/github/netty/protocol/servlet/ServletContext;
    Signature: #424                         // ()Ljava/util/Set<Ljavax/servlet/SessionTrackingMode;>;

  public java.util.Set<javax.servlet.SessionTrackingMode> getEffectiveSessionTrackingModes();
    descriptor: ()Ljava/util/Set;
    flags: ACC_PUBLIC
    Code:
      stack=1, locals=1, args_size=1
         0: aload_0
         1: getfield      #141                // Field sessionTrackingModeSet:Ljava/util/Set;
         4: ifnonnull     12
         7: aload_0
         8: invokevirtual #142                // Method getDefaultSessionTrackingModes:()Ljava/util/Set;
        11: areturn
        12: aload_0
        13: getfield      #141                // Field sessionTrackingModeSet:Ljava/util/Set;
        16: areturn
      LineNumberTable:
        line 502: 0
        line 503: 7
        line 505: 12
      LocalVariableTable:
        Start  Length  Slot  Name   Signature
            0      17     0  this   Lcom/github/netty/protocol/servlet/ServletContext;
      StackMapTable: number_of_entries = 1
        frame_type = 12 /* same */
    Signature: #424                         // ()Ljava/util/Set<Ljavax/servlet/SessionTrackingMode;>;

  public void addListener(java.lang.String);
    descriptor: (Ljava/lang/String;)V
    flags: ACC_PUBLIC
    Code:
      stack=2, locals=3, args_size=2
         0: aload_0
         1: aload_1
         2: invokestatic  #123                // Method java/lang/Class.forName:(Ljava/lang/String;)Ljava/lang/Class;
         5: invokevirtual #143                // Method addListener:(Ljava/lang/Class;)V
         8: goto          16
        11: astore_2
        12: aload_2
        13: invokevirtual #136                // Method java/lang/ClassNotFoundException.printStackTrace:()V
        16: return
      Exception table:
         from    to  target type
             0     8    11   Class java/lang/ClassNotFoundException
      LineNumberTable:
        line 511: 0
        line 514: 8
        line 512: 11
        line 513: 12
        line 515: 16
      LocalVariableTable:
        Start  Length  Slot  Name   Signature
           12       4     2     e   Ljava/lang/ClassNotFoundException;
            0      17     0  this   Lcom/github/netty/protocol/servlet/ServletContext;
            0      17     1 className   Ljava/lang/String;
      StackMapTable: number_of_entries = 2
        frame_type = 75 /* same_locals_1_stack_item */
          stack = [ class java/lang/ClassNotFoundException ]
        frame_type = 4 /* same */

  public <T extends java.util.EventListener> void addListener(T);
    descriptor: (Ljava/util/EventListener;)V
    flags: ACC_PUBLIC
    Code:
      stack=4, locals=3, args_size=2
         0: aload_1
         1: invokestatic  #36                 // Method java/util/Objects.requireNonNull:(Ljava/lang/Object;)Ljava/lang/Object;
         4: pop
         5: aload_0
         6: invokevirtual #115                // Method getServletEventListenerManager:()Lcom/github/netty/protocol/servlet/ServletEventListenerManager;
         9: astore_2
        10: aload_1
        11: instanceof    #144                // class javax/servlet/ServletContextAttributeListener
        14: ifeq          28
        17: aload_2
        18: aload_1
        19: checkcast     #144                // class javax/servlet/ServletContextAttributeListener
        22: invokevirtual #145                // Method com/github/netty/protocol/servlet/ServletEventListenerManager.addServletContextAttributeListener:(Ljavax/servlet/ServletContextAttributeListener;)V
        25: goto          169
        28: aload_1
        29: instanceof    #146                // class javax/servlet/ServletRequestListener
        32: ifeq          46
        35: aload_2
        36: aload_1
        37: checkcast     #146                // class javax/servlet/ServletRequestListener
        40: invokevirtual #147                // Method com/github/netty/protocol/servlet/ServletEventListenerManager.addServletRequestListener:(Ljavax/servlet/ServletRequestListener;)V
        43: goto          169
        46: aload_1
        47: instanceof    #148                // class javax/servlet/ServletRequestAttributeListener
        50: ifeq          64
        53: aload_2
        54: aload_1
        55: checkcast     #148                // class javax/servlet/ServletRequestAttributeListener
        58: invokevirtual #149                // Method com/github/netty/protocol/servlet/ServletEventListenerManager.addServletRequestAttributeListener:(Ljavax/servlet/ServletRequestAttributeListener;)V
        61: goto          169
        64: aload_1
        65: instanceof    #150                // class javax/servlet/http/HttpSessionIdListener
        68: ifeq          82
        71: aload_2
        72: aload_1
        73: checkcast     #150                // class javax/servlet/http/HttpSessionIdListener
        76: invokevirtual #151                // Method com/github/netty/protocol/servlet/ServletEventListenerManager.addHttpSessionIdListenerListener:(Ljavax/servlet/http/HttpSessionIdListener;)V
        79: goto          169
        82: aload_1
        83: instanceof    #152                // class javax/servlet/http/HttpSessionAttributeListener
        86: ifeq          100
        89: aload_2
        90: aload_1
        91: checkcast     #152                // class javax/servlet/http/HttpSessionAttributeListener
        94: invokevirtual #153                // Method com/github/netty/protocol/servlet/ServletEventListenerManager.addHttpSessionAttributeListener:(Ljavax/servlet/http/HttpSessionAttributeListener;)V
        97: goto          169
       100: aload_1
       101: instanceof    #154                // class javax/servlet/http/HttpSessionListener
       104: ifeq          118
       107: aload_2
       108: aload_1
       109: checkcast     #154                // class javax/servlet/http/HttpSessionListener
       112: invokevirtual #155                // Method com/github/netty/protocol/servlet/ServletEventListenerManager.addHttpSessionListener:(Ljavax/servlet/http/HttpSessionListener;)V
       115: goto          169
       118: aload_1
       119: instanceof    #156                // class javax/servlet/ServletContextListener
       122: ifeq          136
       125: aload_2
       126: aload_1
       127: checkcast     #156                // class javax/servlet/ServletContextListener
       130: invokevirtual #157                // Method com/github/netty/protocol/servlet/ServletEventListenerManager.addServletContextListener:(Ljavax/servlet/ServletContextListener;)V
       133: goto          169
       136: new           #158                // class java/lang/IllegalArgumentException
       139: dup
       140: new           #39                 // class java/lang/StringBuilder
       143: dup
       144: invokespecial #40                 // Method java/lang/StringBuilder."<init>":()V
       147: ldc           #159                // String applicationContext.addListener.iae.wrongType
       149: invokevirtual #45                 // Method java/lang/StringBuilder.append:(Ljava/lang/String;)Ljava/lang/StringBuilder;
       152: aload_1
       153: invokevirtual #2                  // Method java/lang/Object.getClass:()Ljava/lang/Class;
       156: invokevirtual #160                // Method java/lang/Class.getName:()Ljava/lang/String;
       159: invokevirtual #45                 // Method java/lang/StringBuilder.append:(Ljava/lang/String;)Ljava/lang/StringBuilder;
       162: invokevirtual #46                 // Method java/lang/StringBuilder.toString:()Ljava/lang/String;
       165: invokespecial #161                // Method java/lang/IllegalArgumentException."<init>":(Ljava/lang/String;)V
       168: athrow
       169: return
      LineNumberTable:
        line 519: 0
        line 521: 5
        line 522: 10
        line 523: 17
        line 525: 28
        line 526: 35
        line 528: 46
        line 529: 53
        line 531: 64
        line 532: 71
        line 534: 82
        line 535: 89
        line 537: 100
        line 538: 107
        line 540: 118
        line 541: 125
        line 544: 136
        line 545: 153
        line 547: 169
      LocalVariableTable:
        Start  Length  Slot  Name   Signature
            0     170     0  this   Lcom/github/netty/protocol/servlet/ServletContext;
            0     170     1 listener   Ljava/util/EventListener;
           10     160     2 listenerManager   Lcom/github/netty/protocol/servlet/ServletEventListenerManager;
      LocalVariableTypeTable:
        Start  Length  Slot  Name   Signature
            0     170     1 listener   TT;
      StackMapTable: number_of_entries = 8
        frame_type = 252 /* append */
          offset_delta = 28
          locals = [ class com/github/netty/protocol/servlet/ServletEventListenerManager ]
        frame_type = 17 /* same */
        frame_type = 17 /* same */
        frame_type = 17 /* same */
        frame_type = 17 /* same */
        frame_type = 17 /* same */
        frame_type = 17 /* same */
        frame_type = 32 /* same */
    Signature: #430                         // <T::Ljava/util/EventListener;>(TT;)V

  public void addListener(java.lang.Class<? extends java.util.EventListener>);
    descriptor: (Ljava/lang/Class;)V
    flags: ACC_PUBLIC
    Code:
      stack=2, locals=3, args_size=2
         0: aload_0
         1: aload_1
         2: invokevirtual #124                // Method java/lang/Class.newInstance:()Ljava/lang/Object;
         5: checkcast     #162                // class java/util/EventListener
         8: invokevirtual #163                // Method addListener:(Ljava/util/EventListener;)V
        11: goto          19
        14: astore_2
        15: aload_2
        16: invokevirtual #130                // Method java/lang/ReflectiveOperationException.printStackTrace:()V
        19: return
      Exception table:
         from    to  target type
             0    11    14   Class java/lang/InstantiationException
             0    11    14   Class java/lang/IllegalAccessException
      LineNumberTable:
        line 552: 0
        line 555: 11
        line 553: 14
        line 554: 15
        line 556: 19
      LocalVariableTable:
        Start  Length  Slot  Name   Signature
           15       4     2     e   Ljava/lang/ReflectiveOperationException;
            0      20     0  this   Lcom/github/netty/protocol/servlet/ServletContext;
            0      20     1 listenerClass   Ljava/lang/Class;
      LocalVariableTypeTable:
        Start  Length  Slot  Name   Signature
            0      20     1 listenerClass   Ljava/lang/Class<+Ljava/util/EventListener;>;
      StackMapTable: number_of_entries = 2
        frame_type = 78 /* same_locals_1_stack_item */
          stack = [ class java/lang/ReflectiveOperationException ]
        frame_type = 4 /* same */
    Signature: #434                         // (Ljava/lang/Class<+Ljava/util/EventListener;>;)V

  public <T extends java.util.EventListener> T createListener(java.lang.Class<T>) throws javax.servlet.ServletException;
    descriptor: (Ljava/lang/Class;)Ljava/util/EventListener;
    flags: ACC_PUBLIC
    Code:
      stack=1, locals=3, args_size=2
         0: aload_1
         1: invokevirtual #124                // Method java/lang/Class.newInstance:()Ljava/lang/Object;
         4: checkcast     #162                // class java/util/EventListener
         7: areturn
         8: astore_2
         9: aload_2
        10: invokevirtual #130                // Method java/lang/ReflectiveOperationException.printStackTrace:()V
        13: aconst_null
        14: areturn
      Exception table:
         from    to  target type
             0     7     8   Class java/lang/InstantiationException
             0     7     8   Class java/lang/IllegalAccessException
      LineNumberTable:
        line 561: 0
        line 562: 8
        line 563: 9
        line 565: 13
      LocalVariableTable:
        Start  Length  Slot  Name   Signature
            9       4     2     e   Ljava/lang/ReflectiveOperationException;
            0      15     0  this   Lcom/github/netty/protocol/servlet/ServletContext;
            0      15     1 clazz   Ljava/lang/Class;
      LocalVariableTypeTable:
        Start  Length  Slot  Name   Signature
            0      15     1 clazz   Ljava/lang/Class<TT;>;
      StackMapTable: number_of_entries = 1
        frame_type = 72 /* same_locals_1_stack_item */
          stack = [ class java/lang/ReflectiveOperationException ]
    Exceptions:
      throws javax.servlet.ServletException
    Signature: #437                         // <T::Ljava/util/EventListener;>(Ljava/lang/Class<TT;>;)TT;

  public javax.servlet.descriptor.JspConfigDescriptor getJspConfigDescriptor();
    descriptor: ()Ljavax/servlet/descriptor/JspConfigDescriptor;
    flags: ACC_PUBLIC
    Code:
      stack=1, locals=1, args_size=1
         0: aconst_null
         1: areturn
      LineNumberTable:
        line 570: 0
      LocalVariableTable:
        Start  Length  Slot  Name   Signature
            0       2     0  this   Lcom/github/netty/protocol/servlet/ServletContext;

  public java.lang.ClassLoader getClassLoader();
    descriptor: ()Ljava/lang/ClassLoader;
    flags: ACC_PUBLIC
    Code:
      stack=1, locals=1, args_size=1
         0: aload_0
         1: getfield      #49                 // Field resourceManager:Lcom/github/netty/core/util/ResourceManager;
         4: invokevirtual #164                // Method com/github/netty/core/util/ResourceManager.getClassLoader:()Ljava/lang/ClassLoader;
         7: areturn
      LineNumberTable:
        line 575: 0
      LocalVariableTable:
        Start  Length  Slot  Name   Signature
            0       8     0  this   Lcom/github/netty/protocol/servlet/ServletContext;

  public void declareRoles(java.lang.String...);
    descriptor: ([Ljava/lang/String;)V
    flags: ACC_PUBLIC, ACC_VARARGS
    Code:
      stack=0, locals=2, args_size=2
         0: return
      LineNumberTable:
        line 581: 0
      LocalVariableTable:
        Start  Length  Slot  Name   Signature
            0       1     0  this   Lcom/github/netty/protocol/servlet/ServletContext;
            0       1     1 roleNames   [Ljava/lang/String;

  public java.lang.String getVirtualServerName();
    descriptor: ()Ljava/lang/String;
    flags: ACC_PUBLIC
    Code:
      stack=2, locals=1, args_size=1
         0: invokestatic  #100                // Method com/github/netty/protocol/servlet/util/ServletUtil.getServerInfo:()Ljava/lang/String;
         3: ldc           #165                // String  (
         5: invokevirtual #102                // Method java/lang/String.concat:(Ljava/lang/String;)Ljava/lang/String;
         8: aload_0
         9: getfield      #38                 // Field servletServerAddress:Ljava/net/InetSocketAddress;
        12: invokevirtual #42                 // Method java/net/InetSocketAddress.getHostName:()Ljava/lang/String;
        15: invokevirtual #102                // Method java/lang/String.concat:(Ljava/lang/String;)Ljava/lang/String;
        18: ldc           #166                // String :
        20: invokevirtual #102                // Method java/lang/String.concat:(Ljava/lang/String;)Ljava/lang/String;
        23: ldc           #167                // String user.name
        25: invokestatic  #168                // Method com/github/netty/core/util/SystemPropertyUtil.get:(Ljava/lang/String;)Ljava/lang/String;
        28: invokevirtual #102                // Method java/lang/String.concat:(Ljava/lang/String;)Ljava/lang/String;
        31: ldc           #108                // String )
        33: invokevirtual #102                // Method java/lang/String.concat:(Ljava/lang/String;)Ljava/lang/String;
        36: areturn
      LineNumberTable:
        line 585: 0
        line 586: 5
        line 587: 12
        line 588: 20
        line 589: 25
        line 590: 33
      LocalVariableTable:
        Start  Length  Slot  Name   Signature
            0      37     0  this   Lcom/github/netty/protocol/servlet/ServletContext;

  public java.lang.String getRequestCharacterEncoding();
    descriptor: ()Ljava/lang/String;
    flags: ACC_PUBLIC
    Code:
      stack=1, locals=1, args_size=1
         0: aload_0
         1: getfield      #169                // Field requestCharacterEncoding:Ljava/lang/String;
         4: ifnonnull     14
         7: getstatic     #170                // Field com/github/netty/protocol/servlet/util/HttpConstants.DEFAULT_CHARSET:Ljava/nio/charset/Charset;
        10: invokevirtual #171                // Method java/nio/charset/Charset.name:()Ljava/lang/String;
        13: areturn
        14: aload_0
        15: getfield      #169                // Field requestCharacterEncoding:Ljava/lang/String;
        18: areturn
      LineNumberTable:
        line 595: 0
        line 596: 7
        line 598: 14
      LocalVariableTable:
        Start  Length  Slot  Name   Signature
            0      19     0  this   Lcom/github/netty/protocol/servlet/ServletContext;
      StackMapTable: number_of_entries = 1
        frame_type = 14 /* same */

  public void setRequestCharacterEncoding(java.lang.String);
    descriptor: (Ljava/lang/String;)V
    flags: ACC_PUBLIC
    Code:
      stack=2, locals=2, args_size=2
         0: aload_0
         1: aload_1
         2: putfield      #169                // Field requestCharacterEncoding:Ljava/lang/String;
         5: return
      LineNumberTable:
        line 603: 0
        line 604: 5
      LocalVariableTable:
        Start  Length  Slot  Name   Signature
            0       6     0  this   Lcom/github/netty/protocol/servlet/ServletContext;
            0       6     1 requestCharacterEncoding   Ljava/lang/String;

  public java.lang.String getResponseCharacterEncoding();
    descriptor: ()Ljava/lang/String;
    flags: ACC_PUBLIC
    Code:
      stack=1, locals=1, args_size=1
         0: aload_0
         1: getfield      #172                // Field responseCharacterEncoding:Ljava/lang/String;
         4: ifnonnull     14
         7: getstatic     #170                // Field com/github/netty/protocol/servlet/util/HttpConstants.DEFAULT_CHARSET:Ljava/nio/charset/Charset;
        10: invokevirtual #171                // Method java/nio/charset/Charset.name:()Ljava/lang/String;
        13: areturn
        14: aload_0
        15: getfield      #172                // Field responseCharacterEncoding:Ljava/lang/String;
        18: areturn
      LineNumberTable:
        line 608: 0
        line 609: 7
        line 611: 14
      LocalVariableTable:
        Start  Length  Slot  Name   Signature
            0      19     0  this   Lcom/github/netty/protocol/servlet/ServletContext;
      StackMapTable: number_of_entries = 1
        frame_type = 14 /* same */

  public void setResponseCharacterEncoding(java.lang.String);
    descriptor: (Ljava/lang/String;)V
    flags: ACC_PUBLIC
    Code:
      stack=2, locals=2, args_size=2
         0: aload_0
         1: aload_1
         2: putfield      #172                // Field responseCharacterEncoding:Ljava/lang/String;
         5: return
      LineNumberTable:
        line 616: 0
        line 617: 5
      LocalVariableTable:
        Start  Length  Slot  Name   Signature
            0       6     0  this   Lcom/github/netty/protocol/servlet/ServletContext;
            0       6     1 responseCharacterEncoding   Ljava/lang/String;

  public javax.servlet.ServletRegistration$Dynamic addJspFile(java.lang.String, java.lang.String);
    descriptor: (Ljava/lang/String;Ljava/lang/String;)Ljavax/servlet/ServletRegistration$Dynamic;
    flags: ACC_PUBLIC
    Code:
      stack=1, locals=3, args_size=3
         0: aconst_null
         1: areturn
      LineNumberTable:
        line 622: 0
      LocalVariableTable:
        Start  Length  Slot  Name   Signature
            0       2     0  this   Lcom/github/netty/protocol/servlet/ServletContext;
            0       2     1 jspName   Ljava/lang/String;
            0       2     2 jspFile   Ljava/lang/String;

  public javax.servlet.SessionCookieConfig getSessionCookieConfig();
    descriptor: ()Ljavax/servlet/SessionCookieConfig;
    flags: ACC_PUBLIC, ACC_BRIDGE, ACC_SYNTHETIC
    Code:
      stack=1, locals=1, args_size=1
         0: aload_0
         1: invokevirtual #173                // Method getSessionCookieConfig:()Lcom/github/netty/protocol/servlet/ServletSessionCookieConfig;
         4: areturn
      LineNumberTable:
        line 26: 0
      LocalVariableTable:
        Start  Length  Slot  Name   Signature
            0       5     0  this   Lcom/github/netty/protocol/servlet/ServletContext;

  public javax.servlet.FilterRegistration$Dynamic addFilter(java.lang.String, java.lang.Class);
    descriptor: (Ljava/lang/String;Ljava/lang/Class;)Ljavax/servlet/FilterRegistration$Dynamic;
    flags: ACC_PUBLIC, ACC_BRIDGE, ACC_SYNTHETIC
    Code:
      stack=3, locals=3, args_size=3
         0: aload_0
         1: aload_1
         2: aload_2
         3: invokevirtual #135                // Method addFilter:(Ljava/lang/String;Ljava/lang/Class;)Lcom/github/netty/protocol/servlet/ServletFilterRegistration;
         6: areturn
      LineNumberTable:
        line 26: 0
      LocalVariableTable:
        Start  Length  Slot  Name   Signature
            0       7     0  this   Lcom/github/netty/protocol/servlet/ServletContext;

  public javax.servlet.FilterRegistration$Dynamic addFilter(java.lang.String, javax.servlet.Filter);
    descriptor: (Ljava/lang/String;Ljavax/servlet/Filter;)Ljavax/servlet/FilterRegistration$Dynamic;
    flags: ACC_PUBLIC, ACC_BRIDGE, ACC_SYNTHETIC
    Code:
      stack=3, locals=3, args_size=3
         0: aload_0
         1: aload_1
         2: aload_2
         3: invokevirtual #139                // Method addFilter:(Ljava/lang/String;Ljavax/servlet/Filter;)Lcom/github/netty/protocol/servlet/ServletFilterRegistration;
         6: areturn
      LineNumberTable:
        line 26: 0
      LocalVariableTable:
        Start  Length  Slot  Name   Signature
            0       7     0  this   Lcom/github/netty/protocol/servlet/ServletContext;

  public javax.servlet.FilterRegistration$Dynamic addFilter(java.lang.String, java.lang.String);
    descriptor: (Ljava/lang/String;Ljava/lang/String;)Ljavax/servlet/FilterRegistration$Dynamic;
    flags: ACC_PUBLIC, ACC_BRIDGE, ACC_SYNTHETIC
    Code:
      stack=3, locals=3, args_size=3
         0: aload_0
         1: aload_1
         2: aload_2
         3: invokevirtual #174                // Method addFilter:(Ljava/lang/String;Ljava/lang/String;)Lcom/github/netty/protocol/servlet/ServletFilterRegistration;
         6: areturn
      LineNumberTable:
        line 26: 0
      LocalVariableTable:
        Start  Length  Slot  Name   Signature
            0       7     0  this   Lcom/github/netty/protocol/servlet/ServletContext;

  public javax.servlet.ServletRegistration getServletRegistration(java.lang.String);
    descriptor: (Ljava/lang/String;)Ljavax/servlet/ServletRegistration;
    flags: ACC_PUBLIC, ACC_BRIDGE, ACC_SYNTHETIC
    Code:
      stack=2, locals=2, args_size=2
         0: aload_0
         1: aload_1
         2: invokevirtual #81                 // Method getServletRegistration:(Ljava/lang/String;)Lcom/github/netty/protocol/servlet/ServletRegistration;
         5: areturn
      LineNumberTable:
        line 26: 0
      LocalVariableTable:
        Start  Length  Slot  Name   Signature
            0       6     0  this   Lcom/github/netty/protocol/servlet/ServletContext;

  public javax.servlet.ServletRegistration$Dynamic addServlet(java.lang.String, java.lang.Class);
    descriptor: (Ljava/lang/String;Ljava/lang/Class;)Ljavax/servlet/ServletRegistration$Dynamic;
    flags: ACC_PUBLIC, ACC_BRIDGE, ACC_SYNTHETIC
    Code:
      stack=3, locals=3, args_size=3
         0: aload_0
         1: aload_1
         2: aload_2
         3: invokevirtual #126                // Method addServlet:(Ljava/lang/String;Ljava/lang/Class;)Lcom/github/netty/protocol/servlet/ServletRegistration;
         6: areturn
      LineNumberTable:
        line 26: 0
      LocalVariableTable:
        Start  Length  Slot  Name   Signature
            0       7     0  this   Lcom/github/netty/protocol/servlet/ServletContext;

  public javax.servlet.ServletRegistration$Dynamic addServlet(java.lang.String, javax.servlet.Servlet);
    descriptor: (Ljava/lang/String;Ljavax/servlet/Servlet;)Ljavax/servlet/ServletRegistration$Dynamic;
    flags: ACC_PUBLIC, ACC_BRIDGE, ACC_SYNTHETIC
    Code:
      stack=3, locals=3, args_size=3
         0: aload_0
         1: aload_1
         2: aload_2
         3: invokevirtual #134                // Method addServlet:(Ljava/lang/String;Ljavax/servlet/Servlet;)Lcom/github/netty/protocol/servlet/ServletRegistration;
         6: areturn
      LineNumberTable:
        line 26: 0
      LocalVariableTable:
        Start  Length  Slot  Name   Signature
            0       7     0  this   Lcom/github/netty/protocol/servlet/ServletContext;

  public javax.servlet.ServletRegistration$Dynamic addServlet(java.lang.String, java.lang.String);
    descriptor: (Ljava/lang/String;Ljava/lang/String;)Ljavax/servlet/ServletRegistration$Dynamic;
    flags: ACC_PUBLIC, ACC_BRIDGE, ACC_SYNTHETIC
    Code:
      stack=3, locals=3, args_size=3
         0: aload_0
         1: aload_1
         2: aload_2
         3: invokevirtual #175                // Method addServlet:(Ljava/lang/String;Ljava/lang/String;)Lcom/github/netty/protocol/servlet/ServletRegistration;
         6: areturn
      LineNumberTable:
        line 26: 0
      LocalVariableTable:
        Start  Length  Slot  Name   Signature
            0       7     0  this   Lcom/github/netty/protocol/servlet/ServletContext;

  public javax.servlet.RequestDispatcher getNamedDispatcher(java.lang.String);
    descriptor: (Ljava/lang/String;)Ljavax/servlet/RequestDispatcher;
    flags: ACC_PUBLIC, ACC_BRIDGE, ACC_SYNTHETIC
    Code:
      stack=2, locals=2, args_size=2
         0: aload_0
         1: aload_1
         2: invokevirtual #176                // Method getNamedDispatcher:(Ljava/lang/String;)Lcom/github/netty/protocol/servlet/ServletRequestDispatcher;
         5: areturn
      LineNumberTable:
        line 26: 0
      LocalVariableTable:
        Start  Length  Slot  Name   Signature
            0       6     0  this   Lcom/github/netty/protocol/servlet/ServletContext;

  public javax.servlet.RequestDispatcher getRequestDispatcher(java.lang.String);
    descriptor: (Ljava/lang/String;)Ljavax/servlet/RequestDispatcher;
    flags: ACC_PUBLIC, ACC_BRIDGE, ACC_SYNTHETIC
    Code:
      stack=2, locals=2, args_size=2
         0: aload_0
         1: aload_1
         2: invokevirtual #177                // Method getRequestDispatcher:(Ljava/lang/String;)Lcom/github/netty/protocol/servlet/ServletRequestDispatcher;
         5: areturn
      LineNumberTable:
        line 26: 0
      LocalVariableTable:
        Start  Length  Slot  Name   Signature
            0       6     0  this   Lcom/github/netty/protocol/servlet/ServletContext;

  public javax.servlet.ServletContext getContext(java.lang.String);
    descriptor: (Ljava/lang/String;)Ljavax/servlet/ServletContext;
    flags: ACC_PUBLIC, ACC_BRIDGE, ACC_SYNTHETIC
    Code:
      stack=2, locals=2, args_size=2
         0: aload_0
         1: aload_1
         2: invokevirtual #178                // Method getContext:(Ljava/lang/String;)Lcom/github/netty/protocol/servlet/ServletContext;
         5: areturn
      LineNumberTable:
        line 26: 0
      LocalVariableTable:
        Start  Length  Slot  Name   Signature
            0       6     0  this   Lcom/github/netty/protocol/servlet/ServletContext;
}
SourceFile: "ServletContext.java"
InnerClasses:
     public static #453= #452 of #667; //Dynamic=class javax/servlet/ServletRegistration$Dynamic of class javax/servlet/ServletRegistration
     public static #453= #459 of #140; //Dynamic=class javax/servlet/FilterRegistration$Dynamic of class javax/servlet/FilterRegistration
